[
  {
    "x": "2021-01-01T00:00:00.000+01:00",
    "AT-Gas In Storage": 73.7331,
    "AT-Gas Capacity": 95.5043
  },
  {
    "x": "2021-01-02T00:00:00.000+01:00",
    "AT-Gas In Storage": 73.2811,
    "AT-Gas Capacity": 95.5266
  },
  {
    "x": "2021-01-03T00:00:00.000+01:00",
    "AT-Gas In Storage": 72.7247,
    "AT-Gas Capacity": 95.5266
  },
  {
    "x": "2021-01-04T00:00:00.000+01:00",
    "AT-Gas In Storage": 71.969,
    "AT-Gas Capacity": 95.5266
  },
  {
    "x": "2021-01-05T00:00:00.000+01:00",
    "AT-Gas In Storage": 71.1417,
    "AT-Gas Capacity": 95.5266
  },
  {
    "x": "2021-01-06T00:00:00.000+01:00",
    "AT-Gas In Storage": 70.3662,
    "AT-Gas Capacity": 95.5266
  },
  {
    "x": "2021-01-07T00:00:00.000+01:00",
    "AT-Gas In Storage": 69.4611,
    "AT-Gas Capacity": 95.5266
  },
  {
    "x": "2021-01-08T00:00:00.000+01:00",
    "AT-Gas In Storage": 68.5525,
    "AT-Gas Capacity": 95.5266
  },
  {
    "x": "2021-01-09T00:00:00.000+01:00",
    "AT-Gas In Storage": 67.8072,
    "AT-Gas Capacity": 95.5266
  },
  {
    "x": "2021-01-10T00:00:00.000+01:00",
    "AT-Gas In Storage": 67.0799,
    "AT-Gas Capacity": 95.5266
  },
  {
    "x": "2021-01-11T00:00:00.000+01:00",
    "AT-Gas In Storage": 66.1594,
    "AT-Gas Capacity": 95.5266
  },
  {
    "x": "2021-01-12T00:00:00.000+01:00",
    "AT-Gas In Storage": 65.2344,
    "AT-Gas Capacity": 95.5266
  },
  {
    "x": "2021-01-13T00:00:00.000+01:00",
    "AT-Gas In Storage": 64.3387,
    "AT-Gas Capacity": 95.5266
  },
  {
    "x": "2021-01-14T00:00:00.000+01:00",
    "AT-Gas In Storage": 63.4554,
    "AT-Gas Capacity": 95.5266
  },
  {
    "x": "2021-01-15T00:00:00.000+01:00",
    "AT-Gas In Storage": 62.5903,
    "AT-Gas Capacity": 95.5266
  },
  {
    "x": "2021-01-16T00:00:00.000+01:00",
    "AT-Gas In Storage": 61.7881,
    "AT-Gas Capacity": 95.5266
  },
  {
    "x": "2021-01-17T00:00:00.000+01:00",
    "AT-Gas In Storage": 60.9934,
    "AT-Gas Capacity": 95.5266
  },
  {
    "x": "2021-01-18T00:00:00.000+01:00",
    "AT-Gas In Storage": 60.0795,
    "AT-Gas Capacity": 95.5266
  },
  {
    "x": "2021-01-19T00:00:00.000+01:00",
    "AT-Gas In Storage": 59.2596,
    "AT-Gas Capacity": 95.5266
  },
  {
    "x": "2021-01-20T00:00:00.000+01:00",
    "AT-Gas In Storage": 58.4608,
    "AT-Gas Capacity": 95.5266
  },
  {
    "x": "2021-01-21T00:00:00.000+01:00",
    "AT-Gas In Storage": 57.752,
    "AT-Gas Capacity": 95.5266
  },
  {
    "x": "2021-01-22T00:00:00.000+01:00",
    "AT-Gas In Storage": 57.1567,
    "AT-Gas Capacity": 95.5266
  },
  {
    "x": "2021-01-23T00:00:00.000+01:00",
    "AT-Gas In Storage": 56.6163,
    "AT-Gas Capacity": 95.5266
  },
  {
    "x": "2021-01-24T00:00:00.000+01:00",
    "AT-Gas In Storage": 56.0329,
    "AT-Gas Capacity": 95.5266
  },
  {
    "x": "2021-01-25T00:00:00.000+01:00",
    "AT-Gas In Storage": 55.1977,
    "AT-Gas Capacity": 95.5266
  },
  {
    "x": "2021-01-26T00:00:00.000+01:00",
    "AT-Gas In Storage": 54.4158,
    "AT-Gas Capacity": 95.5266
  },
  {
    "x": "2021-01-27T00:00:00.000+01:00",
    "AT-Gas In Storage": 53.5746,
    "AT-Gas Capacity": 95.5266
  },
  {
    "x": "2021-01-28T00:00:00.000+01:00",
    "AT-Gas In Storage": 52.853,
    "AT-Gas Capacity": 95.5266
  },
  {
    "x": "2021-01-29T00:00:00.000+01:00",
    "AT-Gas In Storage": 52.3019,
    "AT-Gas Capacity": 95.5266
  },
  {
    "x": "2021-01-30T00:00:00.000+01:00",
    "AT-Gas In Storage": 51.8281,
    "AT-Gas Capacity": 95.5266
  },
  {
    "x": "2021-01-31T00:00:00.000+01:00",
    "AT-Gas In Storage": 51.2899,
    "AT-Gas Capacity": 95.5266
  },
  {
    "x": "2021-02-01T00:00:00.000+01:00",
    "AT-Gas In Storage": 50.5007,
    "AT-Gas Capacity": 95.5266
  },
  {
    "x": "2021-02-02T00:00:00.000+01:00",
    "AT-Gas In Storage": 49.7728,
    "AT-Gas Capacity": 95.5266
  },
  {
    "x": "2021-02-03T00:00:00.000+01:00",
    "AT-Gas In Storage": 49.2468,
    "AT-Gas Capacity": 95.5266
  },
  {
    "x": "2021-02-04T00:00:00.000+01:00",
    "AT-Gas In Storage": 48.798,
    "AT-Gas Capacity": 95.5266
  },
  {
    "x": "2021-02-05T00:00:00.000+01:00",
    "AT-Gas In Storage": 48.3122,
    "AT-Gas Capacity": 95.5266
  },
  {
    "x": "2021-02-06T00:00:00.000+01:00",
    "AT-Gas In Storage": 47.8119,
    "AT-Gas Capacity": 95.5266
  },
  {
    "x": "2021-02-07T00:00:00.000+01:00",
    "AT-Gas In Storage": 47.2811,
    "AT-Gas Capacity": 95.5266
  },
  {
    "x": "2021-02-08T00:00:00.000+01:00",
    "AT-Gas In Storage": 46.5578,
    "AT-Gas Capacity": 95.5266
  },
  {
    "x": "2021-02-09T00:00:00.000+01:00",
    "AT-Gas In Storage": 45.8832,
    "AT-Gas Capacity": 95.5266
  },
  {
    "x": "2021-02-10T00:00:00.000+01:00",
    "AT-Gas In Storage": 45.1368,
    "AT-Gas Capacity": 95.5266
  },
  {
    "x": "2021-02-11T00:00:00.000+01:00",
    "AT-Gas In Storage": 44.2892,
    "AT-Gas Capacity": 95.5266
  },
  {
    "x": "2021-02-12T00:00:00.000+01:00",
    "AT-Gas In Storage": 43.5217,
    "AT-Gas Capacity": 95.5266
  },
  {
    "x": "2021-02-13T00:00:00.000+01:00",
    "AT-Gas In Storage": 42.8684,
    "AT-Gas Capacity": 95.5266
  },
  {
    "x": "2021-02-14T00:00:00.000+01:00",
    "AT-Gas In Storage": 42.2511,
    "AT-Gas Capacity": 95.5266
  },
  {
    "x": "2021-02-15T00:00:00.000+01:00",
    "AT-Gas In Storage": 41.563,
    "AT-Gas Capacity": 95.5266
  },
  {
    "x": "2021-02-16T00:00:00.000+01:00",
    "AT-Gas In Storage": 40.8827,
    "AT-Gas Capacity": 95.5266
  },
  {
    "x": "2021-02-17T00:00:00.000+01:00",
    "AT-Gas In Storage": 40.3143,
    "AT-Gas Capacity": 95.5266
  },
  {
    "x": "2021-02-18T00:00:00.000+01:00",
    "AT-Gas In Storage": 39.7687,
    "AT-Gas Capacity": 95.5266
  },
  {
    "x": "2021-02-19T00:00:00.000+01:00",
    "AT-Gas In Storage": 39.1926,
    "AT-Gas Capacity": 95.5266
  },
  {
    "x": "2021-02-20T00:00:00.000+01:00",
    "AT-Gas In Storage": 38.8038,
    "AT-Gas Capacity": 95.5266
  },
  {
    "x": "2021-02-21T00:00:00.000+01:00",
    "AT-Gas In Storage": 38.4721,
    "AT-Gas Capacity": 95.5266
  },
  {
    "x": "2021-02-22T00:00:00.000+01:00",
    "AT-Gas In Storage": 37.8378,
    "AT-Gas Capacity": 95.5266
  },
  {
    "x": "2021-02-23T00:00:00.000+01:00",
    "AT-Gas In Storage": 37.3556,
    "AT-Gas Capacity": 95.5266
  },
  {
    "x": "2021-02-24T00:00:00.000+01:00",
    "AT-Gas In Storage": 36.9528,
    "AT-Gas Capacity": 95.5266
  },
  {
    "x": "2021-02-25T00:00:00.000+01:00",
    "AT-Gas In Storage": 36.6503,
    "AT-Gas Capacity": 95.5266
  },
  {
    "x": "2021-02-26T00:00:00.000+01:00",
    "AT-Gas In Storage": 36.3497,
    "AT-Gas Capacity": 95.5266
  },
  {
    "x": "2021-02-27T00:00:00.000+01:00",
    "AT-Gas In Storage": 36.1552,
    "AT-Gas Capacity": 95.5266
  },
  {
    "x": "2021-02-28T00:00:00.000+01:00",
    "AT-Gas In Storage": 35.9399,
    "AT-Gas Capacity": 95.5266
  },
  {
    "x": "2021-03-01T00:00:00.000+01:00",
    "AT-Gas In Storage": 35.4771,
    "AT-Gas Capacity": 95.5266
  },
  {
    "x": "2021-03-02T00:00:00.000+01:00",
    "AT-Gas In Storage": 34.9941,
    "AT-Gas Capacity": 95.5266
  },
  {
    "x": "2021-03-03T00:00:00.000+01:00",
    "AT-Gas In Storage": 34.5708,
    "AT-Gas Capacity": 95.5266
  },
  {
    "x": "2021-03-04T00:00:00.000+01:00",
    "AT-Gas In Storage": 34.1969,
    "AT-Gas Capacity": 95.5266
  },
  {
    "x": "2021-03-05T00:00:00.000+01:00",
    "AT-Gas In Storage": 33.7177,
    "AT-Gas Capacity": 95.5266
  },
  {
    "x": "2021-03-06T00:00:00.000+01:00",
    "AT-Gas In Storage": 33.3711,
    "AT-Gas Capacity": 95.5266
  },
  {
    "x": "2021-03-07T00:00:00.000+01:00",
    "AT-Gas In Storage": 33.0253,
    "AT-Gas Capacity": 95.5266
  },
  {
    "x": "2021-03-08T00:00:00.000+01:00",
    "AT-Gas In Storage": 32.4801,
    "AT-Gas Capacity": 95.5266
  },
  {
    "x": "2021-03-09T00:00:00.000+01:00",
    "AT-Gas In Storage": 31.9663,
    "AT-Gas Capacity": 95.5266
  },
  {
    "x": "2021-03-10T00:00:00.000+01:00",
    "AT-Gas In Storage": 31.4602,
    "AT-Gas Capacity": 95.5266
  },
  {
    "x": "2021-03-11T00:00:00.000+01:00",
    "AT-Gas In Storage": 31.0593,
    "AT-Gas Capacity": 95.5266
  },
  {
    "x": "2021-03-12T00:00:00.000+01:00",
    "AT-Gas In Storage": 30.6902,
    "AT-Gas Capacity": 95.5266
  },
  {
    "x": "2021-03-13T00:00:00.000+01:00",
    "AT-Gas In Storage": 30.3696,
    "AT-Gas Capacity": 95.5266
  },
  {
    "x": "2021-03-14T00:00:00.000+01:00",
    "AT-Gas In Storage": 29.9764,
    "AT-Gas Capacity": 95.5266
  },
  {
    "x": "2021-03-15T00:00:00.000+01:00",
    "AT-Gas In Storage": 29.439,
    "AT-Gas Capacity": 95.5266
  },
  {
    "x": "2021-03-16T00:00:00.000+01:00",
    "AT-Gas In Storage": 28.8757,
    "AT-Gas Capacity": 95.5266
  },
  {
    "x": "2021-03-17T00:00:00.000+01:00",
    "AT-Gas In Storage": 28.3241,
    "AT-Gas Capacity": 95.5266
  },
  {
    "x": "2021-03-18T00:00:00.000+01:00",
    "AT-Gas In Storage": 27.7317,
    "AT-Gas Capacity": 95.5266
  },
  {
    "x": "2021-03-19T00:00:00.000+01:00",
    "AT-Gas In Storage": 27.1595,
    "AT-Gas Capacity": 95.5266
  },
  {
    "x": "2021-03-20T00:00:00.000+01:00",
    "AT-Gas In Storage": 26.6192,
    "AT-Gas Capacity": 95.5266
  },
  {
    "x": "2021-03-21T00:00:00.000+01:00",
    "AT-Gas In Storage": 26.1591,
    "AT-Gas Capacity": 95.5266
  },
  {
    "x": "2021-03-22T00:00:00.000+01:00",
    "AT-Gas In Storage": 25.5636,
    "AT-Gas Capacity": 95.5266
  },
  {
    "x": "2021-03-23T00:00:00.000+01:00",
    "AT-Gas In Storage": 25.0945,
    "AT-Gas Capacity": 95.5266
  },
  {
    "x": "2021-03-24T00:00:00.000+01:00",
    "AT-Gas In Storage": 24.6055,
    "AT-Gas Capacity": 95.5266
  },
  {
    "x": "2021-03-25T00:00:00.000+01:00",
    "AT-Gas In Storage": 24.2396,
    "AT-Gas Capacity": 95.5266
  },
  {
    "x": "2021-03-26T00:00:00.000+01:00",
    "AT-Gas In Storage": 24.0218,
    "AT-Gas Capacity": 95.5266
  },
  {
    "x": "2021-03-27T00:00:00.000+01:00",
    "AT-Gas In Storage": 23.9375,
    "AT-Gas Capacity": 94.6899
  },
  {
    "x": "2021-03-28T00:00:00.000+01:00",
    "AT-Gas In Storage": 23.8579,
    "AT-Gas Capacity": 95.5266
  },
  {
    "x": "2021-03-29T00:00:00.000+02:00",
    "AT-Gas In Storage": 23.6857,
    "AT-Gas Capacity": 95.5266
  },
  {
    "x": "2021-03-30T00:00:00.000+02:00",
    "AT-Gas In Storage": 23.574,
    "AT-Gas Capacity": 95.5266
  },
  {
    "x": "2021-03-31T00:00:00.000+02:00",
    "AT-Gas In Storage": 23.5116,
    "AT-Gas Capacity": 95.5266
  },
  {
    "x": "2021-04-01T00:00:00.000+02:00",
    "AT-Gas In Storage": 23.676,
    "AT-Gas Capacity": 95.4801
  },
  {
    "x": "2021-04-02T00:00:00.000+02:00",
    "AT-Gas In Storage": 23.9207,
    "AT-Gas Capacity": 95.4801
  },
  {
    "x": "2021-04-03T00:00:00.000+02:00",
    "AT-Gas In Storage": 24.0741,
    "AT-Gas Capacity": 95.4801
  },
  {
    "x": "2021-04-04T00:00:00.000+02:00",
    "AT-Gas In Storage": 24.2906,
    "AT-Gas Capacity": 95.4801
  },
  {
    "x": "2021-04-05T00:00:00.000+02:00",
    "AT-Gas In Storage": 24.4198,
    "AT-Gas Capacity": 95.4801
  },
  {
    "x": "2021-04-06T00:00:00.000+02:00",
    "AT-Gas In Storage": 24.2023,
    "AT-Gas Capacity": 95.4801
  },
  {
    "x": "2021-04-07T00:00:00.000+02:00",
    "AT-Gas In Storage": 23.9353,
    "AT-Gas Capacity": 95.4801
  },
  {
    "x": "2021-04-08T00:00:00.000+02:00",
    "AT-Gas In Storage": 23.5697,
    "AT-Gas Capacity": 95.4801
  },
  {
    "x": "2021-04-09T00:00:00.000+02:00",
    "AT-Gas In Storage": 23.3007,
    "AT-Gas Capacity": 95.4801
  },
  {
    "x": "2021-04-10T00:00:00.000+02:00",
    "AT-Gas In Storage": 23.1456,
    "AT-Gas Capacity": 95.4801
  },
  {
    "x": "2021-04-11T00:00:00.000+02:00",
    "AT-Gas In Storage": 23.048,
    "AT-Gas Capacity": 95.4801
  },
  {
    "x": "2021-04-12T00:00:00.000+02:00",
    "AT-Gas In Storage": 22.6886,
    "AT-Gas Capacity": 95.4801
  },
  {
    "x": "2021-04-13T00:00:00.000+02:00",
    "AT-Gas In Storage": 22.2568,
    "AT-Gas Capacity": 95.4801
  },
  {
    "x": "2021-04-14T00:00:00.000+02:00",
    "AT-Gas In Storage": 21.9597,
    "AT-Gas Capacity": 95.4801
  },
  {
    "x": "2021-04-15T00:00:00.000+02:00",
    "AT-Gas In Storage": 21.7043,
    "AT-Gas Capacity": 95.4801
  },
  {
    "x": "2021-04-16T00:00:00.000+02:00",
    "AT-Gas In Storage": 21.4396,
    "AT-Gas Capacity": 95.4801
  },
  {
    "x": "2021-04-17T00:00:00.000+02:00",
    "AT-Gas In Storage": 21.3105,
    "AT-Gas Capacity": 95.4801
  },
  {
    "x": "2021-04-18T00:00:00.000+02:00",
    "AT-Gas In Storage": 21.1355,
    "AT-Gas Capacity": 95.4801
  },
  {
    "x": "2021-04-19T00:00:00.000+02:00",
    "AT-Gas In Storage": 20.8683,
    "AT-Gas Capacity": 95.4801
  },
  {
    "x": "2021-04-20T00:00:00.000+02:00",
    "AT-Gas In Storage": 20.6818,
    "AT-Gas Capacity": 95.4801
  },
  {
    "x": "2021-04-21T00:00:00.000+02:00",
    "AT-Gas In Storage": 20.5674,
    "AT-Gas Capacity": 95.4801
  },
  {
    "x": "2021-04-22T00:00:00.000+02:00",
    "AT-Gas In Storage": 20.4181,
    "AT-Gas Capacity": 95.4801
  },
  {
    "x": "2021-04-23T00:00:00.000+02:00",
    "AT-Gas In Storage": 20.3336,
    "AT-Gas Capacity": 95.4801
  },
  {
    "x": "2021-04-24T00:00:00.000+02:00",
    "AT-Gas In Storage": 20.5673,
    "AT-Gas Capacity": 95.4801
  },
  {
    "x": "2021-04-25T00:00:00.000+02:00",
    "AT-Gas In Storage": 20.8298,
    "AT-Gas Capacity": 95.4801
  },
  {
    "x": "2021-04-26T00:00:00.000+02:00",
    "AT-Gas In Storage": 20.7861,
    "AT-Gas Capacity": 95.4801
  },
  {
    "x": "2021-04-27T00:00:00.000+02:00",
    "AT-Gas In Storage": 20.7543,
    "AT-Gas Capacity": 95.4801
  },
  {
    "x": "2021-04-28T00:00:00.000+02:00",
    "AT-Gas In Storage": 20.7378,
    "AT-Gas Capacity": 95.4801
  },
  {
    "x": "2021-04-29T00:00:00.000+02:00",
    "AT-Gas In Storage": 20.734,
    "AT-Gas Capacity": 95.4801
  },
  {
    "x": "2021-04-30T00:00:00.000+02:00",
    "AT-Gas In Storage": 20.6611,
    "AT-Gas Capacity": 95.4801
  },
  {
    "x": "2021-05-01T00:00:00.000+02:00",
    "AT-Gas In Storage": 20.8365,
    "AT-Gas Capacity": 95.4801
  },
  {
    "x": "2021-05-02T00:00:00.000+02:00",
    "AT-Gas In Storage": 20.9907,
    "AT-Gas Capacity": 95.4801
  },
  {
    "x": "2021-05-03T00:00:00.000+02:00",
    "AT-Gas In Storage": 20.9012,
    "AT-Gas Capacity": 95.4801
  },
  {
    "x": "2021-05-04T00:00:00.000+02:00",
    "AT-Gas In Storage": 20.7976,
    "AT-Gas Capacity": 95.4801
  },
  {
    "x": "2021-05-05T00:00:00.000+02:00",
    "AT-Gas In Storage": 20.5958,
    "AT-Gas Capacity": 95.4801
  },
  {
    "x": "2021-05-06T00:00:00.000+02:00",
    "AT-Gas In Storage": 20.2924,
    "AT-Gas Capacity": 95.4801
  },
  {
    "x": "2021-05-07T00:00:00.000+02:00",
    "AT-Gas In Storage": 20.0647,
    "AT-Gas Capacity": 95.4801
  },
  {
    "x": "2021-05-08T00:00:00.000+02:00",
    "AT-Gas In Storage": 20.2286,
    "AT-Gas Capacity": 95.4801
  },
  {
    "x": "2021-05-09T00:00:00.000+02:00",
    "AT-Gas In Storage": 20.5657,
    "AT-Gas Capacity": 95.4801
  },
  {
    "x": "2021-05-10T00:00:00.000+02:00",
    "AT-Gas In Storage": 20.7102,
    "AT-Gas Capacity": 95.4801
  },
  {
    "x": "2021-05-11T00:00:00.000+02:00",
    "AT-Gas In Storage": 20.7535,
    "AT-Gas Capacity": 95.4801
  },
  {
    "x": "2021-05-12T00:00:00.000+02:00",
    "AT-Gas In Storage": 20.7257,
    "AT-Gas Capacity": 95.4801
  },
  {
    "x": "2021-05-13T00:00:00.000+02:00",
    "AT-Gas In Storage": 20.7453,
    "AT-Gas Capacity": 95.4801
  },
  {
    "x": "2021-05-14T00:00:00.000+02:00",
    "AT-Gas In Storage": 20.8986,
    "AT-Gas Capacity": 95.4801
  },
  {
    "x": "2021-05-15T00:00:00.000+02:00",
    "AT-Gas In Storage": 21.0343,
    "AT-Gas Capacity": 95.4801
  },
  {
    "x": "2021-05-16T00:00:00.000+02:00",
    "AT-Gas In Storage": 21.1884,
    "AT-Gas Capacity": 95.4801
  },
  {
    "x": "2021-05-17T00:00:00.000+02:00",
    "AT-Gas In Storage": 21.0702,
    "AT-Gas Capacity": 95.4801
  },
  {
    "x": "2021-05-18T00:00:00.000+02:00",
    "AT-Gas In Storage": 20.8884,
    "AT-Gas Capacity": 95.4801
  },
  {
    "x": "2021-05-19T00:00:00.000+02:00",
    "AT-Gas In Storage": 20.7005,
    "AT-Gas Capacity": 95.4801
  },
  {
    "x": "2021-05-20T00:00:00.000+02:00",
    "AT-Gas In Storage": 20.6061,
    "AT-Gas Capacity": 95.4801
  },
  {
    "x": "2021-05-21T00:00:00.000+02:00",
    "AT-Gas In Storage": 20.6306,
    "AT-Gas Capacity": 95.4801
  },
  {
    "x": "2021-05-22T00:00:00.000+02:00",
    "AT-Gas In Storage": 20.7195,
    "AT-Gas Capacity": 95.4801
  },
  {
    "x": "2021-05-23T00:00:00.000+02:00",
    "AT-Gas In Storage": 20.85,
    "AT-Gas Capacity": 95.4801
  },
  {
    "x": "2021-05-24T00:00:00.000+02:00",
    "AT-Gas In Storage": 20.8008,
    "AT-Gas Capacity": 95.4801
  },
  {
    "x": "2021-05-25T00:00:00.000+02:00",
    "AT-Gas In Storage": 20.6083,
    "AT-Gas Capacity": 95.4801
  },
  {
    "x": "2021-05-26T00:00:00.000+02:00",
    "AT-Gas In Storage": 20.4575,
    "AT-Gas Capacity": 95.4801
  },
  {
    "x": "2021-05-27T00:00:00.000+02:00",
    "AT-Gas In Storage": 20.1585,
    "AT-Gas Capacity": 95.4801
  },
  {
    "x": "2021-05-28T00:00:00.000+02:00",
    "AT-Gas In Storage": 19.9973,
    "AT-Gas Capacity": 95.4801
  },
  {
    "x": "2021-05-29T00:00:00.000+02:00",
    "AT-Gas In Storage": 20.1839,
    "AT-Gas Capacity": 95.4801
  },
  {
    "x": "2021-05-30T00:00:00.000+02:00",
    "AT-Gas In Storage": 20.3867,
    "AT-Gas Capacity": 95.4801
  },
  {
    "x": "2021-05-31T00:00:00.000+02:00",
    "AT-Gas In Storage": 20.4843,
    "AT-Gas Capacity": 95.4801
  },
  {
    "x": "2021-06-01T00:00:00.000+02:00",
    "AT-Gas In Storage": 20.8203,
    "AT-Gas Capacity": 95.4801
  },
  {
    "x": "2021-06-02T00:00:00.000+02:00",
    "AT-Gas In Storage": 21.1875,
    "AT-Gas Capacity": 95.4801
  },
  {
    "x": "2021-06-03T00:00:00.000+02:00",
    "AT-Gas In Storage": 21.5042,
    "AT-Gas Capacity": 95.4801
  },
  {
    "x": "2021-06-04T00:00:00.000+02:00",
    "AT-Gas In Storage": 21.8244,
    "AT-Gas Capacity": 95.4801
  },
  {
    "x": "2021-06-05T00:00:00.000+02:00",
    "AT-Gas In Storage": 22.1922,
    "AT-Gas Capacity": 95.4801
  },
  {
    "x": "2021-06-06T00:00:00.000+02:00",
    "AT-Gas In Storage": 22.5603,
    "AT-Gas Capacity": 95.4801
  },
  {
    "x": "2021-06-07T00:00:00.000+02:00",
    "AT-Gas In Storage": 22.8438,
    "AT-Gas Capacity": 95.4801
  },
  {
    "x": "2021-06-08T00:00:00.000+02:00",
    "AT-Gas In Storage": 23.0957,
    "AT-Gas Capacity": 95.4801
  },
  {
    "x": "2021-06-09T00:00:00.000+02:00",
    "AT-Gas In Storage": 23.2541,
    "AT-Gas Capacity": 95.4801
  },
  {
    "x": "2021-06-10T00:00:00.000+02:00",
    "AT-Gas In Storage": 23.4934,
    "AT-Gas Capacity": 95.4801
  },
  {
    "x": "2021-06-11T00:00:00.000+02:00",
    "AT-Gas In Storage": 23.7498,
    "AT-Gas Capacity": 95.4801
  },
  {
    "x": "2021-06-12T00:00:00.000+02:00",
    "AT-Gas In Storage": 24.2243,
    "AT-Gas Capacity": 95.4801
  },
  {
    "x": "2021-06-13T00:00:00.000+02:00",
    "AT-Gas In Storage": 24.6903,
    "AT-Gas Capacity": 95.4801
  },
  {
    "x": "2021-06-14T00:00:00.000+02:00",
    "AT-Gas In Storage": 25.0474,
    "AT-Gas Capacity": 95.4801
  },
  {
    "x": "2021-06-15T00:00:00.000+02:00",
    "AT-Gas In Storage": 25.2868,
    "AT-Gas Capacity": 95.4801
  },
  {
    "x": "2021-06-16T00:00:00.000+02:00",
    "AT-Gas In Storage": 25.5152,
    "AT-Gas Capacity": 95.4801
  },
  {
    "x": "2021-06-17T00:00:00.000+02:00",
    "AT-Gas In Storage": 25.8441,
    "AT-Gas Capacity": 95.4801
  },
  {
    "x": "2021-06-18T00:00:00.000+02:00",
    "AT-Gas In Storage": 26.2,
    "AT-Gas Capacity": 95.4801
  },
  {
    "x": "2021-06-19T00:00:00.000+02:00",
    "AT-Gas In Storage": 26.5881,
    "AT-Gas Capacity": 95.4801
  },
  {
    "x": "2021-06-20T00:00:00.000+02:00",
    "AT-Gas In Storage": 26.9548,
    "AT-Gas Capacity": 95.4801
  },
  {
    "x": "2021-06-21T00:00:00.000+02:00",
    "AT-Gas In Storage": 27.1602,
    "AT-Gas Capacity": 95.4801
  },
  {
    "x": "2021-06-22T00:00:00.000+02:00",
    "AT-Gas In Storage": 27.2708,
    "AT-Gas Capacity": 95.4801
  },
  {
    "x": "2021-06-23T00:00:00.000+02:00",
    "AT-Gas In Storage": 27.3885,
    "AT-Gas Capacity": 95.4801
  },
  {
    "x": "2021-06-24T00:00:00.000+02:00",
    "AT-Gas In Storage": 27.5065,
    "AT-Gas Capacity": 95.4801
  },
  {
    "x": "2021-06-25T00:00:00.000+02:00",
    "AT-Gas In Storage": 27.649,
    "AT-Gas Capacity": 95.4801
  },
  {
    "x": "2021-06-26T00:00:00.000+02:00",
    "AT-Gas In Storage": 27.9205,
    "AT-Gas Capacity": 95.4801
  },
  {
    "x": "2021-06-27T00:00:00.000+02:00",
    "AT-Gas In Storage": 28.1956,
    "AT-Gas Capacity": 95.4801
  },
  {
    "x": "2021-06-28T00:00:00.000+02:00",
    "AT-Gas In Storage": 28.2956,
    "AT-Gas Capacity": 95.4801
  },
  {
    "x": "2021-06-29T00:00:00.000+02:00",
    "AT-Gas In Storage": 28.3823,
    "AT-Gas Capacity": 95.4801
  },
  {
    "x": "2021-06-30T00:00:00.000+02:00",
    "AT-Gas In Storage": 28.5186,
    "AT-Gas Capacity": 95.4801
  },
  {
    "x": "2021-07-01T00:00:00.000+02:00",
    "AT-Gas In Storage": 28.7485,
    "AT-Gas Capacity": 95.4801
  },
  {
    "x": "2021-07-02T00:00:00.000+02:00",
    "AT-Gas In Storage": 28.813,
    "AT-Gas Capacity": 95.4801
  },
  {
    "x": "2021-07-03T00:00:00.000+02:00",
    "AT-Gas In Storage": 29.0868,
    "AT-Gas Capacity": 95.4801
  },
  {
    "x": "2021-07-04T00:00:00.000+02:00",
    "AT-Gas In Storage": 29.3697,
    "AT-Gas Capacity": 95.4801
  },
  {
    "x": "2021-07-05T00:00:00.000+02:00",
    "AT-Gas In Storage": 29.5907,
    "AT-Gas Capacity": 95.4801
  },
  {
    "x": "2021-07-06T00:00:00.000+02:00",
    "AT-Gas In Storage": 29.6467,
    "AT-Gas Capacity": 95.4801
  },
  {
    "x": "2021-07-07T00:00:00.000+02:00",
    "AT-Gas In Storage": 29.7039,
    "AT-Gas Capacity": 95.4801
  },
  {
    "x": "2021-07-08T00:00:00.000+02:00",
    "AT-Gas In Storage": 29.734,
    "AT-Gas Capacity": 95.4801
  },
  {
    "x": "2021-07-09T00:00:00.000+02:00",
    "AT-Gas In Storage": 29.989,
    "AT-Gas Capacity": 95.4801
  },
  {
    "x": "2021-07-10T00:00:00.000+02:00",
    "AT-Gas In Storage": 30.2969,
    "AT-Gas Capacity": 95.4801
  },
  {
    "x": "2021-07-11T00:00:00.000+02:00",
    "AT-Gas In Storage": 30.646,
    "AT-Gas Capacity": 95.4801
  },
  {
    "x": "2021-07-12T00:00:00.000+02:00",
    "AT-Gas In Storage": 30.755,
    "AT-Gas Capacity": 95.4801
  },
  {
    "x": "2021-07-13T00:00:00.000+02:00",
    "AT-Gas In Storage": 30.6755,
    "AT-Gas Capacity": 95.4801
  },
  {
    "x": "2021-07-14T00:00:00.000+02:00",
    "AT-Gas In Storage": 30.6521,
    "AT-Gas Capacity": 95.4801
  },
  {
    "x": "2021-07-15T00:00:00.000+02:00",
    "AT-Gas In Storage": 30.5392,
    "AT-Gas Capacity": 95.4801
  },
  {
    "x": "2021-07-16T00:00:00.000+02:00",
    "AT-Gas In Storage": 30.6836,
    "AT-Gas Capacity": 95.4801
  },
  {
    "x": "2021-07-17T00:00:00.000+02:00",
    "AT-Gas In Storage": 30.839,
    "AT-Gas Capacity": 95.4801
  },
  {
    "x": "2021-07-18T00:00:00.000+02:00",
    "AT-Gas In Storage": 30.9847,
    "AT-Gas Capacity": 95.4801
  },
  {
    "x": "2021-07-19T00:00:00.000+02:00",
    "AT-Gas In Storage": 31.0817,
    "AT-Gas Capacity": 95.4801
  },
  {
    "x": "2021-07-20T00:00:00.000+02:00",
    "AT-Gas In Storage": 31.0798,
    "AT-Gas Capacity": 95.4801
  },
  {
    "x": "2021-07-21T00:00:00.000+02:00",
    "AT-Gas In Storage": 31.0505,
    "AT-Gas Capacity": 95.4801
  },
  {
    "x": "2021-07-22T00:00:00.000+02:00",
    "AT-Gas In Storage": 31.0427,
    "AT-Gas Capacity": 95.4801
  },
  {
    "x": "2021-07-23T00:00:00.000+02:00",
    "AT-Gas In Storage": 31.2871,
    "AT-Gas Capacity": 95.4801
  },
  {
    "x": "2021-07-24T00:00:00.000+02:00",
    "AT-Gas In Storage": 31.5929,
    "AT-Gas Capacity": 95.4801
  },
  {
    "x": "2021-07-25T00:00:00.000+02:00",
    "AT-Gas In Storage": 31.9259,
    "AT-Gas Capacity": 95.4801
  },
  {
    "x": "2021-07-26T00:00:00.000+02:00",
    "AT-Gas In Storage": 32.1505,
    "AT-Gas Capacity": 95.4801
  },
  {
    "x": "2021-07-27T00:00:00.000+02:00",
    "AT-Gas In Storage": 32.3734,
    "AT-Gas Capacity": 95.4801
  },
  {
    "x": "2021-07-28T00:00:00.000+02:00",
    "AT-Gas In Storage": 32.6221,
    "AT-Gas Capacity": 95.4801
  },
  {
    "x": "2021-07-29T00:00:00.000+02:00",
    "AT-Gas In Storage": 32.9696,
    "AT-Gas Capacity": 95.4801
  },
  {
    "x": "2021-07-30T00:00:00.000+02:00",
    "AT-Gas In Storage": 33.2556,
    "AT-Gas Capacity": 95.4801
  },
  {
    "x": "2021-07-31T00:00:00.000+02:00",
    "AT-Gas In Storage": 33.593,
    "AT-Gas Capacity": 95.4801
  },
  {
    "x": "2021-08-01T00:00:00.000+02:00",
    "AT-Gas In Storage": 33.9951,
    "AT-Gas Capacity": 95.4801
  },
  {
    "x": "2021-08-02T00:00:00.000+02:00",
    "AT-Gas In Storage": 34.2094,
    "AT-Gas Capacity": 95.4801
  },
  {
    "x": "2021-08-03T00:00:00.000+02:00",
    "AT-Gas In Storage": 34.43,
    "AT-Gas Capacity": 95.4801
  },
  {
    "x": "2021-08-04T00:00:00.000+02:00",
    "AT-Gas In Storage": 34.7669,
    "AT-Gas Capacity": 95.4801
  },
  {
    "x": "2021-08-05T00:00:00.000+02:00",
    "AT-Gas In Storage": 35.0474,
    "AT-Gas Capacity": 95.4801
  },
  {
    "x": "2021-08-06T00:00:00.000+02:00",
    "AT-Gas In Storage": 35.3316,
    "AT-Gas Capacity": 95.4801
  },
  {
    "x": "2021-08-07T00:00:00.000+02:00",
    "AT-Gas In Storage": 35.794,
    "AT-Gas Capacity": 95.4801
  },
  {
    "x": "2021-08-08T00:00:00.000+02:00",
    "AT-Gas In Storage": 36.2726,
    "AT-Gas Capacity": 95.4801
  },
  {
    "x": "2021-08-09T00:00:00.000+02:00",
    "AT-Gas In Storage": 36.6438,
    "AT-Gas Capacity": 95.4801
  },
  {
    "x": "2021-08-10T00:00:00.000+02:00",
    "AT-Gas In Storage": 37.0165,
    "AT-Gas Capacity": 95.4801
  },
  {
    "x": "2021-08-11T00:00:00.000+02:00",
    "AT-Gas In Storage": 37.4124,
    "AT-Gas Capacity": 95.4801
  },
  {
    "x": "2021-08-12T00:00:00.000+02:00",
    "AT-Gas In Storage": 37.7977,
    "AT-Gas Capacity": 95.4801
  },
  {
    "x": "2021-08-13T00:00:00.000+02:00",
    "AT-Gas In Storage": 38.1877,
    "AT-Gas Capacity": 95.4801
  },
  {
    "x": "2021-08-14T00:00:00.000+02:00",
    "AT-Gas In Storage": 38.598,
    "AT-Gas Capacity": 95.4801
  },
  {
    "x": "2021-08-15T00:00:00.000+02:00",
    "AT-Gas In Storage": 39.0034,
    "AT-Gas Capacity": 95.4801
  },
  {
    "x": "2021-08-16T00:00:00.000+02:00",
    "AT-Gas In Storage": 39.3113,
    "AT-Gas Capacity": 95.4801
  },
  {
    "x": "2021-08-17T00:00:00.000+02:00",
    "AT-Gas In Storage": 39.6331,
    "AT-Gas Capacity": 95.4801
  },
  {
    "x": "2021-08-18T00:00:00.000+02:00",
    "AT-Gas In Storage": 39.9633,
    "AT-Gas Capacity": 95.4801
  },
  {
    "x": "2021-08-19T00:00:00.000+02:00",
    "AT-Gas In Storage": 40.3543,
    "AT-Gas Capacity": 95.4801
  },
  {
    "x": "2021-08-20T00:00:00.000+02:00",
    "AT-Gas In Storage": 40.7514,
    "AT-Gas Capacity": 95.4801
  },
  {
    "x": "2021-08-21T00:00:00.000+02:00",
    "AT-Gas In Storage": 41.0643,
    "AT-Gas Capacity": 95.4801
  },
  {
    "x": "2021-08-22T00:00:00.000+02:00",
    "AT-Gas In Storage": 41.3834,
    "AT-Gas Capacity": 95.4801
  },
  {
    "x": "2021-08-23T00:00:00.000+02:00",
    "AT-Gas In Storage": 41.6805,
    "AT-Gas Capacity": 95.4801
  },
  {
    "x": "2021-08-24T00:00:00.000+02:00",
    "AT-Gas In Storage": 41.9847,
    "AT-Gas Capacity": 95.4801
  },
  {
    "x": "2021-08-25T00:00:00.000+02:00",
    "AT-Gas In Storage": 42.2166,
    "AT-Gas Capacity": 95.4801
  },
  {
    "x": "2021-08-26T00:00:00.000+02:00",
    "AT-Gas In Storage": 42.5273,
    "AT-Gas Capacity": 95.4801
  },
  {
    "x": "2021-08-27T00:00:00.000+02:00",
    "AT-Gas In Storage": 42.8614,
    "AT-Gas Capacity": 95.4801
  },
  {
    "x": "2021-08-28T00:00:00.000+02:00",
    "AT-Gas In Storage": 43.2697,
    "AT-Gas Capacity": 95.4801
  },
  {
    "x": "2021-08-29T00:00:00.000+02:00",
    "AT-Gas In Storage": 43.7152,
    "AT-Gas Capacity": 95.4801
  },
  {
    "x": "2021-08-30T00:00:00.000+02:00",
    "AT-Gas In Storage": 44.037,
    "AT-Gas Capacity": 95.4801
  },
  {
    "x": "2021-08-31T00:00:00.000+02:00",
    "AT-Gas In Storage": 44.3058,
    "AT-Gas Capacity": 95.4801
  },
  {
    "x": "2021-09-01T00:00:00.000+02:00",
    "AT-Gas In Storage": 44.4411,
    "AT-Gas Capacity": 95.4801
  },
  {
    "x": "2021-09-02T00:00:00.000+02:00",
    "AT-Gas In Storage": 44.6074,
    "AT-Gas Capacity": 95.4801
  },
  {
    "x": "2021-09-03T00:00:00.000+02:00",
    "AT-Gas In Storage": 44.8019,
    "AT-Gas Capacity": 95.4801
  },
  {
    "x": "2021-09-04T00:00:00.000+02:00",
    "AT-Gas In Storage": 45.1387,
    "AT-Gas Capacity": 95.4801
  },
  {
    "x": "2021-09-05T00:00:00.000+02:00",
    "AT-Gas In Storage": 45.5165,
    "AT-Gas Capacity": 95.4801
  },
  {
    "x": "2021-09-06T00:00:00.000+02:00",
    "AT-Gas In Storage": 45.6796,
    "AT-Gas Capacity": 95.4801
  },
  {
    "x": "2021-09-07T00:00:00.000+02:00",
    "AT-Gas In Storage": 45.8185,
    "AT-Gas Capacity": 95.4801
  },
  {
    "x": "2021-09-08T00:00:00.000+02:00",
    "AT-Gas In Storage": 45.9837,
    "AT-Gas Capacity": 95.4801
  },
  {
    "x": "2021-09-09T00:00:00.000+02:00",
    "AT-Gas In Storage": 46.1224,
    "AT-Gas Capacity": 95.4801
  },
  {
    "x": "2021-09-10T00:00:00.000+02:00",
    "AT-Gas In Storage": 46.2468,
    "AT-Gas Capacity": 95.4801
  },
  {
    "x": "2021-09-11T00:00:00.000+02:00",
    "AT-Gas In Storage": 46.5121,
    "AT-Gas Capacity": 95.4801
  },
  {
    "x": "2021-09-12T00:00:00.000+02:00",
    "AT-Gas In Storage": 46.7882,
    "AT-Gas Capacity": 95.4801
  },
  {
    "x": "2021-09-13T00:00:00.000+02:00",
    "AT-Gas In Storage": 46.9034,
    "AT-Gas Capacity": 95.4801
  },
  {
    "x": "2021-09-14T00:00:00.000+02:00",
    "AT-Gas In Storage": 46.9816,
    "AT-Gas Capacity": 95.4801
  },
  {
    "x": "2021-09-15T00:00:00.000+02:00",
    "AT-Gas In Storage": 47.0282,
    "AT-Gas Capacity": 95.4801
  },
  {
    "x": "2021-09-16T00:00:00.000+02:00",
    "AT-Gas In Storage": 47.1085,
    "AT-Gas Capacity": 95.4801
  },
  {
    "x": "2021-09-17T00:00:00.000+02:00",
    "AT-Gas In Storage": 47.3024,
    "AT-Gas Capacity": 95.4801
  },
  {
    "x": "2021-09-18T00:00:00.000+02:00",
    "AT-Gas In Storage": 47.5637,
    "AT-Gas Capacity": 95.4801
  },
  {
    "x": "2021-09-19T00:00:00.000+02:00",
    "AT-Gas In Storage": 47.8338,
    "AT-Gas Capacity": 95.4801
  },
  {
    "x": "2021-09-20T00:00:00.000+02:00",
    "AT-Gas In Storage": 47.9816,
    "AT-Gas Capacity": 95.4801
  },
  {
    "x": "2021-09-21T00:00:00.000+02:00",
    "AT-Gas In Storage": 48.1593,
    "AT-Gas Capacity": 95.4801
  },
  {
    "x": "2021-09-22T00:00:00.000+02:00",
    "AT-Gas In Storage": 48.3374,
    "AT-Gas Capacity": 95.4801
  },
  {
    "x": "2021-09-23T00:00:00.000+02:00",
    "AT-Gas In Storage": 48.5814,
    "AT-Gas Capacity": 95.4801
  },
  {
    "x": "2021-09-24T00:00:00.000+02:00",
    "AT-Gas In Storage": 48.8127,
    "AT-Gas Capacity": 95.4801
  },
  {
    "x": "2021-09-25T00:00:00.000+02:00",
    "AT-Gas In Storage": 49.2307,
    "AT-Gas Capacity": 95.4801
  },
  {
    "x": "2021-09-26T00:00:00.000+02:00",
    "AT-Gas In Storage": 49.6316,
    "AT-Gas Capacity": 95.4801
  },
  {
    "x": "2021-09-27T00:00:00.000+02:00",
    "AT-Gas In Storage": 49.8944,
    "AT-Gas Capacity": 95.4801
  },
  {
    "x": "2021-09-28T00:00:00.000+02:00",
    "AT-Gas In Storage": 50.1719,
    "AT-Gas Capacity": 95.4801
  },
  {
    "x": "2021-09-29T00:00:00.000+02:00",
    "AT-Gas In Storage": 50.442,
    "AT-Gas Capacity": 95.4801
  },
  {
    "x": "2021-09-30T00:00:00.000+02:00",
    "AT-Gas In Storage": 50.8282,
    "AT-Gas Capacity": 95.4801
  },
  {
    "x": "2021-10-01T00:00:00.000+02:00",
    "AT-Gas In Storage": 51.1302,
    "AT-Gas Capacity": 95.4801
  },
  {
    "x": "2021-10-02T00:00:00.000+02:00",
    "AT-Gas In Storage": 51.5798,
    "AT-Gas Capacity": 95.4801
  },
  {
    "x": "2021-10-03T00:00:00.000+02:00",
    "AT-Gas In Storage": 52.0526,
    "AT-Gas Capacity": 95.4801
  },
  {
    "x": "2021-10-04T00:00:00.000+02:00",
    "AT-Gas In Storage": 52.3572,
    "AT-Gas Capacity": 95.4801
  },
  {
    "x": "2021-10-05T00:00:00.000+02:00",
    "AT-Gas In Storage": 52.7557,
    "AT-Gas Capacity": 95.4801
  },
  {
    "x": "2021-10-06T00:00:00.000+02:00",
    "AT-Gas In Storage": 52.9826,
    "AT-Gas Capacity": 95.4801
  },
  {
    "x": "2021-10-07T00:00:00.000+02:00",
    "AT-Gas In Storage": 53.0996,
    "AT-Gas Capacity": 95.4801
  },
  {
    "x": "2021-10-08T00:00:00.000+02:00",
    "AT-Gas In Storage": 53.2821,
    "AT-Gas Capacity": 95.4801
  },
  {
    "x": "2021-10-09T00:00:00.000+02:00",
    "AT-Gas In Storage": 53.5996,
    "AT-Gas Capacity": 95.4801
  },
  {
    "x": "2021-10-10T00:00:00.000+02:00",
    "AT-Gas In Storage": 53.8822,
    "AT-Gas Capacity": 95.4801
  },
  {
    "x": "2021-10-11T00:00:00.000+02:00",
    "AT-Gas In Storage": 54.005,
    "AT-Gas Capacity": 95.4801
  },
  {
    "x": "2021-10-12T00:00:00.000+02:00",
    "AT-Gas In Storage": 54.0315,
    "AT-Gas Capacity": 95.4801
  },
  {
    "x": "2021-10-13T00:00:00.000+02:00",
    "AT-Gas In Storage": 54.0003,
    "AT-Gas Capacity": 95.4801
  },
  {
    "x": "2021-10-14T00:00:00.000+02:00",
    "AT-Gas In Storage": 54.1005,
    "AT-Gas Capacity": 95.4801
  },
  {
    "x": "2021-10-15T00:00:00.000+02:00",
    "AT-Gas In Storage": 54.0946,
    "AT-Gas Capacity": 95.4801
  },
  {
    "x": "2021-10-16T00:00:00.000+02:00",
    "AT-Gas In Storage": 54.1797,
    "AT-Gas Capacity": 95.4801
  },
  {
    "x": "2021-10-17T00:00:00.000+02:00",
    "AT-Gas In Storage": 54.2387,
    "AT-Gas Capacity": 95.4801
  },
  {
    "x": "2021-10-18T00:00:00.000+02:00",
    "AT-Gas In Storage": 54.1011,
    "AT-Gas Capacity": 95.4801
  },
  {
    "x": "2021-10-19T00:00:00.000+02:00",
    "AT-Gas In Storage": 54.112,
    "AT-Gas Capacity": 95.4801
  },
  {
    "x": "2021-10-20T00:00:00.000+02:00",
    "AT-Gas In Storage": 54.2717,
    "AT-Gas Capacity": 95.4801
  },
  {
    "x": "2021-10-21T00:00:00.000+02:00",
    "AT-Gas In Storage": 54.4225,
    "AT-Gas Capacity": 95.4801
  },
  {
    "x": "2021-10-22T00:00:00.000+02:00",
    "AT-Gas In Storage": 54.3639,
    "AT-Gas Capacity": 95.4801
  },
  {
    "x": "2021-10-23T00:00:00.000+02:00",
    "AT-Gas In Storage": 54.3807,
    "AT-Gas Capacity": 95.4801
  },
  {
    "x": "2021-10-24T00:00:00.000+02:00",
    "AT-Gas In Storage": 54.4516,
    "AT-Gas Capacity": 95.4801
  },
  {
    "x": "2021-10-25T00:00:00.000+02:00",
    "AT-Gas In Storage": 54.2874,
    "AT-Gas Capacity": 95.4801
  },
  {
    "x": "2021-10-26T00:00:00.000+02:00",
    "AT-Gas In Storage": 54.0146,
    "AT-Gas Capacity": 95.4801
  },
  {
    "x": "2021-10-27T00:00:00.000+02:00",
    "AT-Gas In Storage": 53.8497,
    "AT-Gas Capacity": 95.4801
  },
  {
    "x": "2021-10-28T00:00:00.000+02:00",
    "AT-Gas In Storage": 53.6557,
    "AT-Gas Capacity": 95.4801
  },
  {
    "x": "2021-10-29T00:00:00.000+02:00",
    "AT-Gas In Storage": 53.5202,
    "AT-Gas Capacity": 95.4801
  },
  {
    "x": "2021-10-30T00:00:00.000+02:00",
    "AT-Gas In Storage": 53.5504,
    "AT-Gas Capacity": 96.3168
  },
  {
    "x": "2021-10-31T00:00:00.000+02:00",
    "AT-Gas In Storage": 53.6219,
    "AT-Gas Capacity": 95.4801
  },
  {
    "x": "2021-11-01T00:00:00.000+01:00",
    "AT-Gas In Storage": 53.5655,
    "AT-Gas Capacity": 95.4801
  },
  {
    "x": "2021-11-02T00:00:00.000+01:00",
    "AT-Gas In Storage": 53.1762,
    "AT-Gas Capacity": 95.4801
  },
  {
    "x": "2021-11-03T00:00:00.000+01:00",
    "AT-Gas In Storage": 52.7696,
    "AT-Gas Capacity": 95.4801
  },
  {
    "x": "2021-11-04T00:00:00.000+01:00",
    "AT-Gas In Storage": 52.4433,
    "AT-Gas Capacity": 95.4801
  },
  {
    "x": "2021-11-05T00:00:00.000+01:00",
    "AT-Gas In Storage": 52.1638,
    "AT-Gas Capacity": 95.4801
  },
  {
    "x": "2021-11-06T00:00:00.000+01:00",
    "AT-Gas In Storage": 52.0166,
    "AT-Gas Capacity": 95.4801
  },
  {
    "x": "2021-11-07T00:00:00.000+01:00",
    "AT-Gas In Storage": 51.9205,
    "AT-Gas Capacity": 95.4801
  },
  {
    "x": "2021-11-08T00:00:00.000+01:00",
    "AT-Gas In Storage": 51.5473,
    "AT-Gas Capacity": 95.4801
  },
  {
    "x": "2021-11-09T00:00:00.000+01:00",
    "AT-Gas In Storage": 51.2369,
    "AT-Gas Capacity": 95.4801
  },
  {
    "x": "2021-11-10T00:00:00.000+01:00",
    "AT-Gas In Storage": 51.0589,
    "AT-Gas Capacity": 95.4801
  },
  {
    "x": "2021-11-11T00:00:00.000+01:00",
    "AT-Gas In Storage": 50.7701,
    "AT-Gas Capacity": 95.4801
  },
  {
    "x": "2021-11-12T00:00:00.000+01:00",
    "AT-Gas In Storage": 50.535,
    "AT-Gas Capacity": 95.4801
  },
  {
    "x": "2021-11-13T00:00:00.000+01:00",
    "AT-Gas In Storage": 50.4082,
    "AT-Gas Capacity": 95.4801
  },
  {
    "x": "2021-11-14T00:00:00.000+01:00",
    "AT-Gas In Storage": 50.3464,
    "AT-Gas Capacity": 95.4801
  },
  {
    "x": "2021-11-15T00:00:00.000+01:00",
    "AT-Gas In Storage": 49.999,
    "AT-Gas Capacity": 95.4801
  },
  {
    "x": "2021-11-16T00:00:00.000+01:00",
    "AT-Gas In Storage": 49.6849,
    "AT-Gas Capacity": 95.4801
  },
  {
    "x": "2021-11-17T00:00:00.000+01:00",
    "AT-Gas In Storage": 49.33,
    "AT-Gas Capacity": 95.4801
  },
  {
    "x": "2021-11-18T00:00:00.000+01:00",
    "AT-Gas In Storage": 48.9351,
    "AT-Gas Capacity": 95.4801
  },
  {
    "x": "2021-11-19T00:00:00.000+01:00",
    "AT-Gas In Storage": 48.7636,
    "AT-Gas Capacity": 95.4801
  },
  {
    "x": "2021-11-20T00:00:00.000+01:00",
    "AT-Gas In Storage": 48.6681,
    "AT-Gas Capacity": 95.4801
  },
  {
    "x": "2021-11-21T00:00:00.000+01:00",
    "AT-Gas In Storage": 48.5271,
    "AT-Gas Capacity": 95.4801
  },
  {
    "x": "2021-11-22T00:00:00.000+01:00",
    "AT-Gas In Storage": 48.0912,
    "AT-Gas Capacity": 95.4801
  },
  {
    "x": "2021-11-23T00:00:00.000+01:00",
    "AT-Gas In Storage": 47.6801,
    "AT-Gas Capacity": 95.4801
  },
  {
    "x": "2021-11-24T00:00:00.000+01:00",
    "AT-Gas In Storage": 47.1847,
    "AT-Gas Capacity": 95.4801
  },
  {
    "x": "2021-11-25T00:00:00.000+01:00",
    "AT-Gas In Storage": 46.6042,
    "AT-Gas Capacity": 95.4801
  },
  {
    "x": "2021-11-26T00:00:00.000+01:00",
    "AT-Gas In Storage": 46.0531,
    "AT-Gas Capacity": 95.4801
  },
  {
    "x": "2021-11-27T00:00:00.000+01:00",
    "AT-Gas In Storage": 45.6572,
    "AT-Gas Capacity": 95.4801
  },
  {
    "x": "2021-11-28T00:00:00.000+01:00",
    "AT-Gas In Storage": 45.2828,
    "AT-Gas Capacity": 95.4801
  },
  {
    "x": "2021-11-29T00:00:00.000+01:00",
    "AT-Gas In Storage": 44.6811,
    "AT-Gas Capacity": 95.4801
  },
  {
    "x": "2021-11-30T00:00:00.000+01:00",
    "AT-Gas In Storage": 44.0037,
    "AT-Gas Capacity": 95.4801
  },
  {
    "x": "2021-12-01T00:00:00.000+01:00",
    "AT-Gas In Storage": 43.4312,
    "AT-Gas Capacity": 95.4801
  },
  {
    "x": "2021-12-02T00:00:00.000+01:00",
    "AT-Gas In Storage": 42.7565,
    "AT-Gas Capacity": 95.4801
  },
  {
    "x": "2021-12-03T00:00:00.000+01:00",
    "AT-Gas In Storage": 42.21,
    "AT-Gas Capacity": 95.4801
  },
  {
    "x": "2021-12-04T00:00:00.000+01:00",
    "AT-Gas In Storage": 41.7949,
    "AT-Gas Capacity": 95.4801
  },
  {
    "x": "2021-12-05T00:00:00.000+01:00",
    "AT-Gas In Storage": 41.4683,
    "AT-Gas Capacity": 95.4801
  },
  {
    "x": "2021-12-06T00:00:00.000+01:00",
    "AT-Gas In Storage": 40.7674,
    "AT-Gas Capacity": 95.4801
  },
  {
    "x": "2021-12-07T00:00:00.000+01:00",
    "AT-Gas In Storage": 40.0976,
    "AT-Gas Capacity": 95.4801
  },
  {
    "x": "2021-12-08T00:00:00.000+01:00",
    "AT-Gas In Storage": 39.5369,
    "AT-Gas Capacity": 95.4801
  },
  {
    "x": "2021-12-09T00:00:00.000+01:00",
    "AT-Gas In Storage": 38.844,
    "AT-Gas Capacity": 95.4801
  },
  {
    "x": "2021-12-10T00:00:00.000+01:00",
    "AT-Gas In Storage": 38.2477,
    "AT-Gas Capacity": 95.4801
  },
  {
    "x": "2021-12-11T00:00:00.000+01:00",
    "AT-Gas In Storage": 37.8857,
    "AT-Gas Capacity": 95.4801
  },
  {
    "x": "2021-12-12T00:00:00.000+01:00",
    "AT-Gas In Storage": 37.6574,
    "AT-Gas Capacity": 95.4801
  },
  {
    "x": "2021-12-13T00:00:00.000+01:00",
    "AT-Gas In Storage": 37.2573,
    "AT-Gas Capacity": 95.4801
  },
  {
    "x": "2021-12-14T00:00:00.000+01:00",
    "AT-Gas In Storage": 36.9583,
    "AT-Gas Capacity": 95.4801
  },
  {
    "x": "2021-12-15T00:00:00.000+01:00",
    "AT-Gas In Storage": 36.7035,
    "AT-Gas Capacity": 95.4801
  },
  {
    "x": "2021-12-16T00:00:00.000+01:00",
    "AT-Gas In Storage": 36.2913,
    "AT-Gas Capacity": 95.4801
  },
  {
    "x": "2021-12-17T00:00:00.000+01:00",
    "AT-Gas In Storage": 35.938,
    "AT-Gas Capacity": 95.4801
  },
  {
    "x": "2021-12-18T00:00:00.000+01:00",
    "AT-Gas In Storage": 35.7041,
    "AT-Gas Capacity": 95.4801
  },
  {
    "x": "2021-12-19T00:00:00.000+01:00",
    "AT-Gas In Storage": 35.4066,
    "AT-Gas Capacity": 95.4801
  },
  {
    "x": "2021-12-20T00:00:00.000+01:00",
    "AT-Gas In Storage": 34.7563,
    "AT-Gas Capacity": 95.4801
  },
  {
    "x": "2021-12-21T00:00:00.000+01:00",
    "AT-Gas In Storage": 33.9985,
    "AT-Gas Capacity": 95.4801
  },
  {
    "x": "2021-12-22T00:00:00.000+01:00",
    "AT-Gas In Storage": 33.2782,
    "AT-Gas Capacity": 95.4801
  },
  {
    "x": "2021-12-23T00:00:00.000+01:00",
    "AT-Gas In Storage": 32.6717,
    "AT-Gas Capacity": 95.4801
  },
  {
    "x": "2021-12-24T00:00:00.000+01:00",
    "AT-Gas In Storage": 32.3909,
    "AT-Gas Capacity": 95.4801
  },
  {
    "x": "2021-12-25T00:00:00.000+01:00",
    "AT-Gas In Storage": 32.2666,
    "AT-Gas Capacity": 95.4801
  },
  {
    "x": "2021-12-26T00:00:00.000+01:00",
    "AT-Gas In Storage": 32.0619,
    "AT-Gas Capacity": 95.4801
  },
  {
    "x": "2021-12-27T00:00:00.000+01:00",
    "AT-Gas In Storage": 31.8543,
    "AT-Gas Capacity": 95.4801
  },
  {
    "x": "2021-12-28T00:00:00.000+01:00",
    "AT-Gas In Storage": 31.7945,
    "AT-Gas Capacity": 95.4801
  },
  {
    "x": "2021-12-29T00:00:00.000+01:00",
    "AT-Gas In Storage": 31.9065,
    "AT-Gas Capacity": 95.4801
  },
  {
    "x": "2021-12-30T00:00:00.000+01:00",
    "AT-Gas In Storage": 32.1473,
    "AT-Gas Capacity": 95.4801
  }
]