[
  {
    "x": "2023-01-01T00:00:00.000+01:00",
    "DK1-Price": 2.01,
    "DK2-Price": 2.01
  },
  {
    "x": "2023-01-01T01:00:00.000+01:00",
    "DK1-Price": 1.38,
    "DK2-Price": 1.38
  },
  {
    "x": "2023-01-01T02:00:00.000+01:00",
    "DK1-Price": 0.09,
    "DK2-Price": 0.09
  },
  {
    "x": "2023-01-01T03:00:00.000+01:00",
    "DK1-Price": 0.08,
    "DK2-Price": 0.08
  },
  {
    "x": "2023-01-01T04:00:00.000+01:00",
    "DK1-Price": 0.05,
    "DK2-Price": 0.05
  },
  {
    "x": "2023-01-01T05:00:00.000+01:00",
    "DK1-Price": 0,
    "DK2-Price": 0.08
  },
  {
    "x": "2023-01-01T06:00:00.000+01:00",
    "DK1-Price": -0.38,
    "DK2-Price": 0.09
  },
  {
    "x": "2023-01-01T07:00:00.000+01:00",
    "DK1-Price": 0,
    "DK2-Price": 0.53
  },
  {
    "x": "2023-01-01T08:00:00.000+01:00",
    "DK1-Price": 0,
    "DK2-Price": 2.03
  },
  {
    "x": "2023-01-01T09:00:00.000+01:00",
    "DK1-Price": 0.04,
    "DK2-Price": 3.1
  },
  {
    "x": "2023-01-01T10:00:00.000+01:00",
    "DK1-Price": 0.8,
    "DK2-Price": 4.43
  },
  {
    "x": "2023-01-01T11:00:00.000+01:00",
    "DK1-Price": 0.08,
    "DK2-Price": 6.06
  },
  {
    "x": "2023-01-01T12:00:00.000+01:00",
    "DK1-Price": 0.04,
    "DK2-Price": 6.06
  },
  {
    "x": "2023-01-01T13:00:00.000+01:00",
    "DK1-Price": 0,
    "DK2-Price": 5.68
  },
  {
    "x": "2023-01-01T14:00:00.000+01:00",
    "DK1-Price": 0.85,
    "DK2-Price": 17.71
  },
  {
    "x": "2023-01-01T15:00:00.000+01:00",
    "DK1-Price": 23.53,
    "DK2-Price": 24.11
  },
  {
    "x": "2023-01-01T16:00:00.000+01:00",
    "DK1-Price": 36.54,
    "DK2-Price": 36.54
  },
  {
    "x": "2023-01-01T17:00:00.000+01:00",
    "DK1-Price": 46.03,
    "DK2-Price": 46.03
  },
  {
    "x": "2023-01-01T18:00:00.000+01:00",
    "DK1-Price": 55.57,
    "DK2-Price": 55.57
  },
  {
    "x": "2023-01-01T19:00:00.000+01:00",
    "DK1-Price": 54.95,
    "DK2-Price": 54.95
  },
  {
    "x": "2023-01-01T20:00:00.000+01:00",
    "DK1-Price": 49.23,
    "DK2-Price": 49.23
  },
  {
    "x": "2023-01-01T21:00:00.000+01:00",
    "DK1-Price": 44.99,
    "DK2-Price": 44.99
  },
  {
    "x": "2023-01-01T22:00:00.000+01:00",
    "DK1-Price": 45.96,
    "DK2-Price": 45.96
  },
  {
    "x": "2023-01-01T23:00:00.000+01:00",
    "DK1-Price": 35,
    "DK2-Price": 35
  },
  {
    "x": "2023-01-02T00:00:00.000+01:00",
    "DK1-Price": 57.91,
    "DK2-Price": 57.91
  },
  {
    "x": "2023-01-02T01:00:00.000+01:00",
    "DK1-Price": 51.67,
    "DK2-Price": 51.67
  },
  {
    "x": "2023-01-02T02:00:00.000+01:00",
    "DK1-Price": 52.93,
    "DK2-Price": 52.86
  },
  {
    "x": "2023-01-02T03:00:00.000+01:00",
    "DK1-Price": 44.16,
    "DK2-Price": 44.16
  },
  {
    "x": "2023-01-02T04:00:00.000+01:00",
    "DK1-Price": 50.08,
    "DK2-Price": 50.08
  },
  {
    "x": "2023-01-02T05:00:00.000+01:00",
    "DK1-Price": 77.09,
    "DK2-Price": 70.73
  },
  {
    "x": "2023-01-02T06:00:00.000+01:00",
    "DK1-Price": 105.08,
    "DK2-Price": 104.08
  },
  {
    "x": "2023-01-02T07:00:00.000+01:00",
    "DK1-Price": 140.64,
    "DK2-Price": 140.64
  },
  {
    "x": "2023-01-02T08:00:00.000+01:00",
    "DK1-Price": 145.98,
    "DK2-Price": 145.98
  },
  {
    "x": "2023-01-02T09:00:00.000+01:00",
    "DK1-Price": 147.05,
    "DK2-Price": 147.05
  },
  {
    "x": "2023-01-02T10:00:00.000+01:00",
    "DK1-Price": 145.61,
    "DK2-Price": 145.61
  },
  {
    "x": "2023-01-02T11:00:00.000+01:00",
    "DK1-Price": 143.35,
    "DK2-Price": 143.35
  },
  {
    "x": "2023-01-02T12:00:00.000+01:00",
    "DK1-Price": 144.38,
    "DK2-Price": 144.38
  },
  {
    "x": "2023-01-02T13:00:00.000+01:00",
    "DK1-Price": 143.76,
    "DK2-Price": 143.76
  },
  {
    "x": "2023-01-02T14:00:00.000+01:00",
    "DK1-Price": 148.2,
    "DK2-Price": 148.2
  },
  {
    "x": "2023-01-02T15:00:00.000+01:00",
    "DK1-Price": 155.34,
    "DK2-Price": 155.34
  },
  {
    "x": "2023-01-02T16:00:00.000+01:00",
    "DK1-Price": 162.89,
    "DK2-Price": 162.89
  },
  {
    "x": "2023-01-02T17:00:00.000+01:00",
    "DK1-Price": 170,
    "DK2-Price": 170
  },
  {
    "x": "2023-01-02T18:00:00.000+01:00",
    "DK1-Price": 174.74,
    "DK2-Price": 174.74
  },
  {
    "x": "2023-01-02T19:00:00.000+01:00",
    "DK1-Price": 164.46,
    "DK2-Price": 164.46
  },
  {
    "x": "2023-01-02T20:00:00.000+01:00",
    "DK1-Price": 153,
    "DK2-Price": 153
  },
  {
    "x": "2023-01-02T21:00:00.000+01:00",
    "DK1-Price": 141.67,
    "DK2-Price": 141.67
  },
  {
    "x": "2023-01-02T22:00:00.000+01:00",
    "DK1-Price": 134.91,
    "DK2-Price": 131.67
  },
  {
    "x": "2023-01-02T23:00:00.000+01:00",
    "DK1-Price": 124.22,
    "DK2-Price": 118.06
  },
  {
    "x": "2023-01-03T00:00:00.000+01:00",
    "DK1-Price": 130.01,
    "DK2-Price": 78.81
  },
  {
    "x": "2023-01-03T01:00:00.000+01:00",
    "DK1-Price": 120,
    "DK2-Price": 73.93
  },
  {
    "x": "2023-01-03T02:00:00.000+01:00",
    "DK1-Price": 118.76,
    "DK2-Price": 73.94
  },
  {
    "x": "2023-01-03T03:00:00.000+01:00",
    "DK1-Price": 115,
    "DK2-Price": 71.44
  },
  {
    "x": "2023-01-03T04:00:00.000+01:00",
    "DK1-Price": 113.63,
    "DK2-Price": 72.33
  },
  {
    "x": "2023-01-03T05:00:00.000+01:00",
    "DK1-Price": 116.27,
    "DK2-Price": 77.14
  },
  {
    "x": "2023-01-03T06:00:00.000+01:00",
    "DK1-Price": 138.92,
    "DK2-Price": 102.48
  },
  {
    "x": "2023-01-03T07:00:00.000+01:00",
    "DK1-Price": 159.92,
    "DK2-Price": 154.96
  },
  {
    "x": "2023-01-03T08:00:00.000+01:00",
    "DK1-Price": 169.17,
    "DK2-Price": 163.92
  },
  {
    "x": "2023-01-03T09:00:00.000+01:00",
    "DK1-Price": 171.18,
    "DK2-Price": 167.07
  },
  {
    "x": "2023-01-03T10:00:00.000+01:00",
    "DK1-Price": 168.57,
    "DK2-Price": 168.57
  },
  {
    "x": "2023-01-03T11:00:00.000+01:00",
    "DK1-Price": 169.49,
    "DK2-Price": 169.49
  },
  {
    "x": "2023-01-03T12:00:00.000+01:00",
    "DK1-Price": 164.5,
    "DK2-Price": 164.5
  },
  {
    "x": "2023-01-03T13:00:00.000+01:00",
    "DK1-Price": 160.91,
    "DK2-Price": 160.91
  },
  {
    "x": "2023-01-03T14:00:00.000+01:00",
    "DK1-Price": 163.06,
    "DK2-Price": 163.06
  },
  {
    "x": "2023-01-03T15:00:00.000+01:00",
    "DK1-Price": 167.73,
    "DK2-Price": 167.73
  },
  {
    "x": "2023-01-03T16:00:00.000+01:00",
    "DK1-Price": 166.61,
    "DK2-Price": 166.61
  },
  {
    "x": "2023-01-03T17:00:00.000+01:00",
    "DK1-Price": 170.72,
    "DK2-Price": 170.72
  },
  {
    "x": "2023-01-03T18:00:00.000+01:00",
    "DK1-Price": 168.93,
    "DK2-Price": 168.93
  },
  {
    "x": "2023-01-03T19:00:00.000+01:00",
    "DK1-Price": 160.99,
    "DK2-Price": 160.99
  },
  {
    "x": "2023-01-03T20:00:00.000+01:00",
    "DK1-Price": 149.62,
    "DK2-Price": 149.62
  },
  {
    "x": "2023-01-03T21:00:00.000+01:00",
    "DK1-Price": 130.99,
    "DK2-Price": 131.05
  },
  {
    "x": "2023-01-03T22:00:00.000+01:00",
    "DK1-Price": 114.27,
    "DK2-Price": 114.27
  },
  {
    "x": "2023-01-03T23:00:00.000+01:00",
    "DK1-Price": 93.66,
    "DK2-Price": 93.66
  },
  {
    "x": "2023-01-04T00:00:00.000+01:00",
    "DK1-Price": 80.89,
    "DK2-Price": 82.88
  },
  {
    "x": "2023-01-04T01:00:00.000+01:00",
    "DK1-Price": 70.67,
    "DK2-Price": 78.84
  },
  {
    "x": "2023-01-04T02:00:00.000+01:00",
    "DK1-Price": 40,
    "DK2-Price": 69.93
  },
  {
    "x": "2023-01-04T03:00:00.000+01:00",
    "DK1-Price": 8.68,
    "DK2-Price": 69.26
  },
  {
    "x": "2023-01-04T04:00:00.000+01:00",
    "DK1-Price": 0.85,
    "DK2-Price": 71.75
  },
  {
    "x": "2023-01-04T05:00:00.000+01:00",
    "DK1-Price": 11.02,
    "DK2-Price": 81.73
  },
  {
    "x": "2023-01-04T06:00:00.000+01:00",
    "DK1-Price": 61.02,
    "DK2-Price": 80.11
  },
  {
    "x": "2023-01-04T07:00:00.000+01:00",
    "DK1-Price": 79.2,
    "DK2-Price": 83.33
  },
  {
    "x": "2023-01-04T08:00:00.000+01:00",
    "DK1-Price": 84.2,
    "DK2-Price": 86.27
  },
  {
    "x": "2023-01-04T09:00:00.000+01:00",
    "DK1-Price": 83.32,
    "DK2-Price": 85.37
  },
  {
    "x": "2023-01-04T10:00:00.000+01:00",
    "DK1-Price": 70.07,
    "DK2-Price": 75.95
  },
  {
    "x": "2023-01-04T11:00:00.000+01:00",
    "DK1-Price": 79.74,
    "DK2-Price": 81.71
  },
  {
    "x": "2023-01-04T12:00:00.000+01:00",
    "DK1-Price": 80.89,
    "DK2-Price": 80.89
  },
  {
    "x": "2023-01-04T13:00:00.000+01:00",
    "DK1-Price": 79.72,
    "DK2-Price": 79.72
  },
  {
    "x": "2023-01-04T14:00:00.000+01:00",
    "DK1-Price": 80.22,
    "DK2-Price": 80.22
  },
  {
    "x": "2023-01-04T15:00:00.000+01:00",
    "DK1-Price": 79.74,
    "DK2-Price": 79.74
  },
  {
    "x": "2023-01-04T16:00:00.000+01:00",
    "DK1-Price": 80.82,
    "DK2-Price": 80.82
  },
  {
    "x": "2023-01-04T17:00:00.000+01:00",
    "DK1-Price": 86.16,
    "DK2-Price": 86.16
  },
  {
    "x": "2023-01-04T18:00:00.000+01:00",
    "DK1-Price": 72.28,
    "DK2-Price": 72.28
  },
  {
    "x": "2023-01-04T19:00:00.000+01:00",
    "DK1-Price": 66.61,
    "DK2-Price": 66.61
  },
  {
    "x": "2023-01-04T20:00:00.000+01:00",
    "DK1-Price": 43.2,
    "DK2-Price": 62.13
  },
  {
    "x": "2023-01-04T21:00:00.000+01:00",
    "DK1-Price": 31.25,
    "DK2-Price": 57.26
  },
  {
    "x": "2023-01-04T22:00:00.000+01:00",
    "DK1-Price": 34.96,
    "DK2-Price": 37.94
  },
  {
    "x": "2023-01-04T23:00:00.000+01:00",
    "DK1-Price": 9.09,
    "DK2-Price": 30.82
  },
  {
    "x": "2023-01-05T00:00:00.000+01:00",
    "DK1-Price": 0.09,
    "DK2-Price": 30.03
  },
  {
    "x": "2023-01-05T01:00:00.000+01:00",
    "DK1-Price": 0.1,
    "DK2-Price": 28.15
  },
  {
    "x": "2023-01-05T02:00:00.000+01:00",
    "DK1-Price": 0.12,
    "DK2-Price": 27.68
  },
  {
    "x": "2023-01-05T03:00:00.000+01:00",
    "DK1-Price": 0.12,
    "DK2-Price": 27.76
  },
  {
    "x": "2023-01-05T04:00:00.000+01:00",
    "DK1-Price": 2.23,
    "DK2-Price": 28.63
  },
  {
    "x": "2023-01-05T05:00:00.000+01:00",
    "DK1-Price": 10.07,
    "DK2-Price": 17.73
  },
  {
    "x": "2023-01-05T06:00:00.000+01:00",
    "DK1-Price": 61.04,
    "DK2-Price": 62.7
  },
  {
    "x": "2023-01-05T07:00:00.000+01:00",
    "DK1-Price": 87.19,
    "DK2-Price": 85.53
  },
  {
    "x": "2023-01-05T08:00:00.000+01:00",
    "DK1-Price": 95.84,
    "DK2-Price": 93.54
  },
  {
    "x": "2023-01-05T09:00:00.000+01:00",
    "DK1-Price": 125.55,
    "DK2-Price": 107.92
  },
  {
    "x": "2023-01-05T10:00:00.000+01:00",
    "DK1-Price": 131.92,
    "DK2-Price": 128.75
  },
  {
    "x": "2023-01-05T11:00:00.000+01:00",
    "DK1-Price": 143.07,
    "DK2-Price": 139.64
  },
  {
    "x": "2023-01-05T12:00:00.000+01:00",
    "DK1-Price": 140.91,
    "DK2-Price": 139.99
  },
  {
    "x": "2023-01-05T13:00:00.000+01:00",
    "DK1-Price": 142.58,
    "DK2-Price": 142.58
  },
  {
    "x": "2023-01-05T14:00:00.000+01:00",
    "DK1-Price": 151.03,
    "DK2-Price": 149.4
  },
  {
    "x": "2023-01-05T15:00:00.000+01:00",
    "DK1-Price": 159.48,
    "DK2-Price": 155.2
  },
  {
    "x": "2023-01-05T16:00:00.000+01:00",
    "DK1-Price": 172.73,
    "DK2-Price": 172.73
  },
  {
    "x": "2023-01-05T17:00:00.000+01:00",
    "DK1-Price": 194.7,
    "DK2-Price": 194.7
  },
  {
    "x": "2023-01-05T18:00:00.000+01:00",
    "DK1-Price": 194.67,
    "DK2-Price": 194.67
  },
  {
    "x": "2023-01-05T19:00:00.000+01:00",
    "DK1-Price": 177.98,
    "DK2-Price": 177.98
  },
  {
    "x": "2023-01-05T20:00:00.000+01:00",
    "DK1-Price": 163.99,
    "DK2-Price": 163.99
  },
  {
    "x": "2023-01-05T21:00:00.000+01:00",
    "DK1-Price": 152,
    "DK2-Price": 152
  },
  {
    "x": "2023-01-05T22:00:00.000+01:00",
    "DK1-Price": 144.64,
    "DK2-Price": 144.64
  },
  {
    "x": "2023-01-05T23:00:00.000+01:00",
    "DK1-Price": 127,
    "DK2-Price": 127
  },
  {
    "x": "2023-01-06T00:00:00.000+01:00",
    "DK1-Price": 107.21,
    "DK2-Price": 107.21
  },
  {
    "x": "2023-01-06T01:00:00.000+01:00",
    "DK1-Price": 101.1,
    "DK2-Price": 101.1
  },
  {
    "x": "2023-01-06T02:00:00.000+01:00",
    "DK1-Price": 96.73,
    "DK2-Price": 96.73
  },
  {
    "x": "2023-01-06T03:00:00.000+01:00",
    "DK1-Price": 82.34,
    "DK2-Price": 82.34
  },
  {
    "x": "2023-01-06T04:00:00.000+01:00",
    "DK1-Price": 81.93,
    "DK2-Price": 81.93
  },
  {
    "x": "2023-01-06T05:00:00.000+01:00",
    "DK1-Price": 84.03,
    "DK2-Price": 84.03
  },
  {
    "x": "2023-01-06T06:00:00.000+01:00",
    "DK1-Price": 97.25,
    "DK2-Price": 97.25
  },
  {
    "x": "2023-01-06T07:00:00.000+01:00",
    "DK1-Price": 106.51,
    "DK2-Price": 103.95
  },
  {
    "x": "2023-01-06T08:00:00.000+01:00",
    "DK1-Price": 120.7,
    "DK2-Price": 108.51
  },
  {
    "x": "2023-01-06T09:00:00.000+01:00",
    "DK1-Price": 116.86,
    "DK2-Price": 109.92
  },
  {
    "x": "2023-01-06T10:00:00.000+01:00",
    "DK1-Price": 112.85,
    "DK2-Price": 110.14
  },
  {
    "x": "2023-01-06T11:00:00.000+01:00",
    "DK1-Price": 113.37,
    "DK2-Price": 110.65
  },
  {
    "x": "2023-01-06T12:00:00.000+01:00",
    "DK1-Price": 115,
    "DK2-Price": 109.91
  },
  {
    "x": "2023-01-06T13:00:00.000+01:00",
    "DK1-Price": 109.78,
    "DK2-Price": 101.09
  },
  {
    "x": "2023-01-06T14:00:00.000+01:00",
    "DK1-Price": 119.71,
    "DK2-Price": 113.06
  },
  {
    "x": "2023-01-06T15:00:00.000+01:00",
    "DK1-Price": 125.83,
    "DK2-Price": 122.81
  },
  {
    "x": "2023-01-06T16:00:00.000+01:00",
    "DK1-Price": 139.57,
    "DK2-Price": 135.62
  },
  {
    "x": "2023-01-06T17:00:00.000+01:00",
    "DK1-Price": 155.22,
    "DK2-Price": 150.72
  },
  {
    "x": "2023-01-06T18:00:00.000+01:00",
    "DK1-Price": 150.09,
    "DK2-Price": 142.11
  },
  {
    "x": "2023-01-06T19:00:00.000+01:00",
    "DK1-Price": 146.15,
    "DK2-Price": 119.92
  },
  {
    "x": "2023-01-06T20:00:00.000+01:00",
    "DK1-Price": 139.1,
    "DK2-Price": 107.22
  },
  {
    "x": "2023-01-06T21:00:00.000+01:00",
    "DK1-Price": 131.8,
    "DK2-Price": 101.02
  },
  {
    "x": "2023-01-06T22:00:00.000+01:00",
    "DK1-Price": 129.94,
    "DK2-Price": 74.25
  },
  {
    "x": "2023-01-06T23:00:00.000+01:00",
    "DK1-Price": 121.3,
    "DK2-Price": 94.8
  },
  {
    "x": "2023-01-07T00:00:00.000+01:00",
    "DK1-Price": 97.15,
    "DK2-Price": 71.67
  },
  {
    "x": "2023-01-07T01:00:00.000+01:00",
    "DK1-Price": 98.43,
    "DK2-Price": 69.93
  },
  {
    "x": "2023-01-07T02:00:00.000+01:00",
    "DK1-Price": 96.05,
    "DK2-Price": 96.05
  },
  {
    "x": "2023-01-07T03:00:00.000+01:00",
    "DK1-Price": 87.97,
    "DK2-Price": 87.97
  },
  {
    "x": "2023-01-07T04:00:00.000+01:00",
    "DK1-Price": 82.99,
    "DK2-Price": 82.99
  },
  {
    "x": "2023-01-07T05:00:00.000+01:00",
    "DK1-Price": 83.59,
    "DK2-Price": 83.59
  },
  {
    "x": "2023-01-07T06:00:00.000+01:00",
    "DK1-Price": 90.76,
    "DK2-Price": 90.76
  },
  {
    "x": "2023-01-07T07:00:00.000+01:00",
    "DK1-Price": 103.21,
    "DK2-Price": 103.21
  },
  {
    "x": "2023-01-07T08:00:00.000+01:00",
    "DK1-Price": 111.86,
    "DK2-Price": 111.86
  },
  {
    "x": "2023-01-07T09:00:00.000+01:00",
    "DK1-Price": 112,
    "DK2-Price": 112
  },
  {
    "x": "2023-01-07T10:00:00.000+01:00",
    "DK1-Price": 100,
    "DK2-Price": 100
  },
  {
    "x": "2023-01-07T11:00:00.000+01:00",
    "DK1-Price": 88.32,
    "DK2-Price": 88.32
  },
  {
    "x": "2023-01-07T12:00:00.000+01:00",
    "DK1-Price": 87.9,
    "DK2-Price": 87.9
  },
  {
    "x": "2023-01-07T13:00:00.000+01:00",
    "DK1-Price": 94.05,
    "DK2-Price": 91.79
  },
  {
    "x": "2023-01-07T14:00:00.000+01:00",
    "DK1-Price": 88.98,
    "DK2-Price": 80.51
  },
  {
    "x": "2023-01-07T15:00:00.000+01:00",
    "DK1-Price": 85.56,
    "DK2-Price": 78.94
  },
  {
    "x": "2023-01-07T16:00:00.000+01:00",
    "DK1-Price": 94.1,
    "DK2-Price": 79.93
  },
  {
    "x": "2023-01-07T17:00:00.000+01:00",
    "DK1-Price": 96.81,
    "DK2-Price": 78.68
  },
  {
    "x": "2023-01-07T18:00:00.000+01:00",
    "DK1-Price": 99.52,
    "DK2-Price": 78.38
  },
  {
    "x": "2023-01-07T19:00:00.000+01:00",
    "DK1-Price": 94.58,
    "DK2-Price": 74.39
  },
  {
    "x": "2023-01-07T20:00:00.000+01:00",
    "DK1-Price": 87.86,
    "DK2-Price": 66.98
  },
  {
    "x": "2023-01-07T21:00:00.000+01:00",
    "DK1-Price": 61.47,
    "DK2-Price": 59.99
  },
  {
    "x": "2023-01-07T22:00:00.000+01:00",
    "DK1-Price": 50,
    "DK2-Price": 48.8
  },
  {
    "x": "2023-01-07T23:00:00.000+01:00",
    "DK1-Price": 38.25,
    "DK2-Price": 35.9
  },
  {
    "x": "2023-01-08T00:00:00.000+01:00",
    "DK1-Price": 10.93,
    "DK2-Price": 24.44
  },
  {
    "x": "2023-01-08T01:00:00.000+01:00",
    "DK1-Price": 9.07,
    "DK2-Price": 9.3
  },
  {
    "x": "2023-01-08T02:00:00.000+01:00",
    "DK1-Price": 9.1,
    "DK2-Price": 9.1
  },
  {
    "x": "2023-01-08T03:00:00.000+01:00",
    "DK1-Price": 4.16,
    "DK2-Price": 4.16
  },
  {
    "x": "2023-01-08T04:00:00.000+01:00",
    "DK1-Price": 5.58,
    "DK2-Price": 5.58
  },
  {
    "x": "2023-01-08T05:00:00.000+01:00",
    "DK1-Price": 9.92,
    "DK2-Price": 9.92
  },
  {
    "x": "2023-01-08T06:00:00.000+01:00",
    "DK1-Price": 9.02,
    "DK2-Price": 9.02
  },
  {
    "x": "2023-01-08T07:00:00.000+01:00",
    "DK1-Price": 16.47,
    "DK2-Price": 16.47
  },
  {
    "x": "2023-01-08T08:00:00.000+01:00",
    "DK1-Price": 49.42,
    "DK2-Price": 27.08
  },
  {
    "x": "2023-01-08T09:00:00.000+01:00",
    "DK1-Price": 82.8,
    "DK2-Price": 29.08
  },
  {
    "x": "2023-01-08T10:00:00.000+01:00",
    "DK1-Price": 93.7,
    "DK2-Price": 35.22
  },
  {
    "x": "2023-01-08T11:00:00.000+01:00",
    "DK1-Price": 103.87,
    "DK2-Price": 70.19
  },
  {
    "x": "2023-01-08T12:00:00.000+01:00",
    "DK1-Price": 101.69,
    "DK2-Price": 49.08
  },
  {
    "x": "2023-01-08T13:00:00.000+01:00",
    "DK1-Price": 99,
    "DK2-Price": 65.13
  },
  {
    "x": "2023-01-08T14:00:00.000+01:00",
    "DK1-Price": 104.29,
    "DK2-Price": 62.19
  },
  {
    "x": "2023-01-08T15:00:00.000+01:00",
    "DK1-Price": 103.64,
    "DK2-Price": 63.49
  },
  {
    "x": "2023-01-08T16:00:00.000+01:00",
    "DK1-Price": 109.11,
    "DK2-Price": 86.29
  },
  {
    "x": "2023-01-08T17:00:00.000+01:00",
    "DK1-Price": 118.04,
    "DK2-Price": 118.04
  },
  {
    "x": "2023-01-08T18:00:00.000+01:00",
    "DK1-Price": 122.61,
    "DK2-Price": 122.61
  },
  {
    "x": "2023-01-08T19:00:00.000+01:00",
    "DK1-Price": 109.11,
    "DK2-Price": 65.62
  },
  {
    "x": "2023-01-08T20:00:00.000+01:00",
    "DK1-Price": 103.93,
    "DK2-Price": 60.98
  },
  {
    "x": "2023-01-08T21:00:00.000+01:00",
    "DK1-Price": 98.43,
    "DK2-Price": 60.31
  },
  {
    "x": "2023-01-08T22:00:00.000+01:00",
    "DK1-Price": 99.37,
    "DK2-Price": 69.4
  },
  {
    "x": "2023-01-08T23:00:00.000+01:00",
    "DK1-Price": 81.34,
    "DK2-Price": 48.89
  },
  {
    "x": "2023-01-09T00:00:00.000+01:00",
    "DK1-Price": 75.13,
    "DK2-Price": 75.13
  },
  {
    "x": "2023-01-09T01:00:00.000+01:00",
    "DK1-Price": 64.38,
    "DK2-Price": 64.38
  },
  {
    "x": "2023-01-09T02:00:00.000+01:00",
    "DK1-Price": 60.28,
    "DK2-Price": 60.28
  },
  {
    "x": "2023-01-09T03:00:00.000+01:00",
    "DK1-Price": 39.41,
    "DK2-Price": 39.41
  },
  {
    "x": "2023-01-09T04:00:00.000+01:00",
    "DK1-Price": 47.25,
    "DK2-Price": 47.34
  },
  {
    "x": "2023-01-09T05:00:00.000+01:00",
    "DK1-Price": 69.07,
    "DK2-Price": 68.99
  },
  {
    "x": "2023-01-09T06:00:00.000+01:00",
    "DK1-Price": 107.13,
    "DK2-Price": 107.13
  },
  {
    "x": "2023-01-09T07:00:00.000+01:00",
    "DK1-Price": 160,
    "DK2-Price": 160
  },
  {
    "x": "2023-01-09T08:00:00.000+01:00",
    "DK1-Price": 180,
    "DK2-Price": 180
  },
  {
    "x": "2023-01-09T09:00:00.000+01:00",
    "DK1-Price": 177.14,
    "DK2-Price": 177.14
  },
  {
    "x": "2023-01-09T10:00:00.000+01:00",
    "DK1-Price": 159.07,
    "DK2-Price": 159.07
  },
  {
    "x": "2023-01-09T11:00:00.000+01:00",
    "DK1-Price": 160.57,
    "DK2-Price": 160.57
  },
  {
    "x": "2023-01-09T12:00:00.000+01:00",
    "DK1-Price": 140.56,
    "DK2-Price": 140.56
  },
  {
    "x": "2023-01-09T13:00:00.000+01:00",
    "DK1-Price": 137.67,
    "DK2-Price": 137.67
  },
  {
    "x": "2023-01-09T14:00:00.000+01:00",
    "DK1-Price": 143.57,
    "DK2-Price": 143.57
  },
  {
    "x": "2023-01-09T15:00:00.000+01:00",
    "DK1-Price": 151.02,
    "DK2-Price": 151.02
  },
  {
    "x": "2023-01-09T16:00:00.000+01:00",
    "DK1-Price": 161.96,
    "DK2-Price": 161.96
  },
  {
    "x": "2023-01-09T17:00:00.000+01:00",
    "DK1-Price": 174.34,
    "DK2-Price": 174.34
  },
  {
    "x": "2023-01-09T18:00:00.000+01:00",
    "DK1-Price": 182.18,
    "DK2-Price": 182.18
  },
  {
    "x": "2023-01-09T19:00:00.000+01:00",
    "DK1-Price": 170.24,
    "DK2-Price": 157.7
  },
  {
    "x": "2023-01-09T20:00:00.000+01:00",
    "DK1-Price": 160.51,
    "DK2-Price": 145.07
  },
  {
    "x": "2023-01-09T21:00:00.000+01:00",
    "DK1-Price": 138.93,
    "DK2-Price": 134.62
  },
  {
    "x": "2023-01-09T22:00:00.000+01:00",
    "DK1-Price": 132,
    "DK2-Price": 83.84
  },
  {
    "x": "2023-01-09T23:00:00.000+01:00",
    "DK1-Price": 108.31,
    "DK2-Price": 80.59
  },
  {
    "x": "2023-01-10T00:00:00.000+01:00",
    "DK1-Price": 106.02,
    "DK2-Price": 106.02
  },
  {
    "x": "2023-01-10T01:00:00.000+01:00",
    "DK1-Price": 96.71,
    "DK2-Price": 96.71
  },
  {
    "x": "2023-01-10T02:00:00.000+01:00",
    "DK1-Price": 95.14,
    "DK2-Price": 95.14
  },
  {
    "x": "2023-01-10T03:00:00.000+01:00",
    "DK1-Price": 90.36,
    "DK2-Price": 90.36
  },
  {
    "x": "2023-01-10T04:00:00.000+01:00",
    "DK1-Price": 95.61,
    "DK2-Price": 95.61
  },
  {
    "x": "2023-01-10T05:00:00.000+01:00",
    "DK1-Price": 108.6,
    "DK2-Price": 91.02
  },
  {
    "x": "2023-01-10T06:00:00.000+01:00",
    "DK1-Price": 138.13,
    "DK2-Price": 134.81
  },
  {
    "x": "2023-01-10T07:00:00.000+01:00",
    "DK1-Price": 154.73,
    "DK2-Price": 154.73
  },
  {
    "x": "2023-01-10T08:00:00.000+01:00",
    "DK1-Price": 165.33,
    "DK2-Price": 165.33
  },
  {
    "x": "2023-01-10T09:00:00.000+01:00",
    "DK1-Price": 160.42,
    "DK2-Price": 156.57
  },
  {
    "x": "2023-01-10T10:00:00.000+01:00",
    "DK1-Price": 154.73,
    "DK2-Price": 151.02
  },
  {
    "x": "2023-01-10T11:00:00.000+01:00",
    "DK1-Price": 146.45,
    "DK2-Price": 142.94
  },
  {
    "x": "2023-01-10T12:00:00.000+01:00",
    "DK1-Price": 141.22,
    "DK2-Price": 140.07
  },
  {
    "x": "2023-01-10T13:00:00.000+01:00",
    "DK1-Price": 141.68,
    "DK2-Price": 139.97
  },
  {
    "x": "2023-01-10T14:00:00.000+01:00",
    "DK1-Price": 145.41,
    "DK2-Price": 141.92
  },
  {
    "x": "2023-01-10T15:00:00.000+01:00",
    "DK1-Price": 145.92,
    "DK2-Price": 142.42
  },
  {
    "x": "2023-01-10T16:00:00.000+01:00",
    "DK1-Price": 140.11,
    "DK2-Price": 139.31
  },
  {
    "x": "2023-01-10T17:00:00.000+01:00",
    "DK1-Price": 146.34,
    "DK2-Price": 146.34
  },
  {
    "x": "2023-01-10T18:00:00.000+01:00",
    "DK1-Price": 138.8,
    "DK2-Price": 137.08
  },
  {
    "x": "2023-01-10T19:00:00.000+01:00",
    "DK1-Price": 124.44,
    "DK2-Price": 121.46
  },
  {
    "x": "2023-01-10T20:00:00.000+01:00",
    "DK1-Price": 106.15,
    "DK2-Price": 105.64
  },
  {
    "x": "2023-01-10T21:00:00.000+01:00",
    "DK1-Price": 86.53,
    "DK2-Price": 86.53
  },
  {
    "x": "2023-01-10T22:00:00.000+01:00",
    "DK1-Price": 81.3,
    "DK2-Price": 79.35
  },
  {
    "x": "2023-01-10T23:00:00.000+01:00",
    "DK1-Price": 42.96,
    "DK2-Price": 44.91
  },
  {
    "x": "2023-01-11T00:00:00.000+01:00",
    "DK1-Price": 5,
    "DK2-Price": 42.03
  },
  {
    "x": "2023-01-11T01:00:00.000+01:00",
    "DK1-Price": 0.16,
    "DK2-Price": 27.73
  },
  {
    "x": "2023-01-11T02:00:00.000+01:00",
    "DK1-Price": 0.08,
    "DK2-Price": 25.17
  },
  {
    "x": "2023-01-11T03:00:00.000+01:00",
    "DK1-Price": 0.01,
    "DK2-Price": 22.57
  },
  {
    "x": "2023-01-11T04:00:00.000+01:00",
    "DK1-Price": 0.04,
    "DK2-Price": 25.49
  },
  {
    "x": "2023-01-11T05:00:00.000+01:00",
    "DK1-Price": 2.75,
    "DK2-Price": 26.6
  },
  {
    "x": "2023-01-11T06:00:00.000+01:00",
    "DK1-Price": 57.88,
    "DK2-Price": 48.54
  },
  {
    "x": "2023-01-11T07:00:00.000+01:00",
    "DK1-Price": 91.11,
    "DK2-Price": 71.49
  },
  {
    "x": "2023-01-11T08:00:00.000+01:00",
    "DK1-Price": 127.44,
    "DK2-Price": 72.71
  },
  {
    "x": "2023-01-11T09:00:00.000+01:00",
    "DK1-Price": 126.54,
    "DK2-Price": 69.96
  },
  {
    "x": "2023-01-11T10:00:00.000+01:00",
    "DK1-Price": 127.63,
    "DK2-Price": 68.89
  },
  {
    "x": "2023-01-11T11:00:00.000+01:00",
    "DK1-Price": 124.81,
    "DK2-Price": 69.29
  },
  {
    "x": "2023-01-11T12:00:00.000+01:00",
    "DK1-Price": 117.47,
    "DK2-Price": 68.86
  },
  {
    "x": "2023-01-11T13:00:00.000+01:00",
    "DK1-Price": 110.54,
    "DK2-Price": 66.8
  },
  {
    "x": "2023-01-11T14:00:00.000+01:00",
    "DK1-Price": 115.74,
    "DK2-Price": 69.52
  },
  {
    "x": "2023-01-11T15:00:00.000+01:00",
    "DK1-Price": 117.7,
    "DK2-Price": 75.91
  },
  {
    "x": "2023-01-11T16:00:00.000+01:00",
    "DK1-Price": 119.2,
    "DK2-Price": 119.2
  },
  {
    "x": "2023-01-11T17:00:00.000+01:00",
    "DK1-Price": 128.28,
    "DK2-Price": 128.28
  },
  {
    "x": "2023-01-11T18:00:00.000+01:00",
    "DK1-Price": 128.76,
    "DK2-Price": 106.48
  },
  {
    "x": "2023-01-11T19:00:00.000+01:00",
    "DK1-Price": 122.7,
    "DK2-Price": 67.99
  },
  {
    "x": "2023-01-11T20:00:00.000+01:00",
    "DK1-Price": 114.56,
    "DK2-Price": 65.16
  },
  {
    "x": "2023-01-11T21:00:00.000+01:00",
    "DK1-Price": 93.47,
    "DK2-Price": 60.01
  },
  {
    "x": "2023-01-11T22:00:00.000+01:00",
    "DK1-Price": 91.71,
    "DK2-Price": 49.91
  },
  {
    "x": "2023-01-11T23:00:00.000+01:00",
    "DK1-Price": 68.54,
    "DK2-Price": 43.32
  },
  {
    "x": "2023-01-12T00:00:00.000+01:00",
    "DK1-Price": 19.88,
    "DK2-Price": 19.88
  },
  {
    "x": "2023-01-12T01:00:00.000+01:00",
    "DK1-Price": 5.55,
    "DK2-Price": 5.55
  },
  {
    "x": "2023-01-12T02:00:00.000+01:00",
    "DK1-Price": 4.69,
    "DK2-Price": 4.69
  },
  {
    "x": "2023-01-12T03:00:00.000+01:00",
    "DK1-Price": 0.1,
    "DK2-Price": 0.1
  },
  {
    "x": "2023-01-12T04:00:00.000+01:00",
    "DK1-Price": 2.73,
    "DK2-Price": 2.73
  },
  {
    "x": "2023-01-12T05:00:00.000+01:00",
    "DK1-Price": 24.94,
    "DK2-Price": 24.94
  },
  {
    "x": "2023-01-12T06:00:00.000+01:00",
    "DK1-Price": 85.72,
    "DK2-Price": 36.01
  },
  {
    "x": "2023-01-12T07:00:00.000+01:00",
    "DK1-Price": 111.55,
    "DK2-Price": 59.98
  },
  {
    "x": "2023-01-12T08:00:00.000+01:00",
    "DK1-Price": 106.83,
    "DK2-Price": 65.18
  },
  {
    "x": "2023-01-12T09:00:00.000+01:00",
    "DK1-Price": 97.83,
    "DK2-Price": 65.03
  },
  {
    "x": "2023-01-12T10:00:00.000+01:00",
    "DK1-Price": 99.81,
    "DK2-Price": 66.3
  },
  {
    "x": "2023-01-12T11:00:00.000+01:00",
    "DK1-Price": 101.1,
    "DK2-Price": 66.72
  },
  {
    "x": "2023-01-12T12:00:00.000+01:00",
    "DK1-Price": 100.19,
    "DK2-Price": 66.6
  },
  {
    "x": "2023-01-12T13:00:00.000+01:00",
    "DK1-Price": 99.64,
    "DK2-Price": 70.85
  },
  {
    "x": "2023-01-12T14:00:00.000+01:00",
    "DK1-Price": 100.77,
    "DK2-Price": 73.76
  },
  {
    "x": "2023-01-12T15:00:00.000+01:00",
    "DK1-Price": 102.13,
    "DK2-Price": 92.89
  },
  {
    "x": "2023-01-12T16:00:00.000+01:00",
    "DK1-Price": 101.43,
    "DK2-Price": 96.7
  },
  {
    "x": "2023-01-12T17:00:00.000+01:00",
    "DK1-Price": 112.01,
    "DK2-Price": 109.94
  },
  {
    "x": "2023-01-12T18:00:00.000+01:00",
    "DK1-Price": 119.49,
    "DK2-Price": 116.62
  },
  {
    "x": "2023-01-12T19:00:00.000+01:00",
    "DK1-Price": 100.79,
    "DK2-Price": 98.37
  },
  {
    "x": "2023-01-12T20:00:00.000+01:00",
    "DK1-Price": 99.35,
    "DK2-Price": 74.08
  },
  {
    "x": "2023-01-12T21:00:00.000+01:00",
    "DK1-Price": 84.77,
    "DK2-Price": 74.5
  },
  {
    "x": "2023-01-12T22:00:00.000+01:00",
    "DK1-Price": 70.43,
    "DK2-Price": 66.84
  },
  {
    "x": "2023-01-12T23:00:00.000+01:00",
    "DK1-Price": 39.57,
    "DK2-Price": 42.49
  },
  {
    "x": "2023-01-13T00:00:00.000+01:00",
    "DK1-Price": 32.64,
    "DK2-Price": 32.64
  },
  {
    "x": "2023-01-13T01:00:00.000+01:00",
    "DK1-Price": 16.99,
    "DK2-Price": 21.87
  },
  {
    "x": "2023-01-13T02:00:00.000+01:00",
    "DK1-Price": 9,
    "DK2-Price": 16.54
  },
  {
    "x": "2023-01-13T03:00:00.000+01:00",
    "DK1-Price": 2.65,
    "DK2-Price": 18.46
  },
  {
    "x": "2023-01-13T04:00:00.000+01:00",
    "DK1-Price": 3.35,
    "DK2-Price": 24.82
  },
  {
    "x": "2023-01-13T05:00:00.000+01:00",
    "DK1-Price": 25.26,
    "DK2-Price": 30.32
  },
  {
    "x": "2023-01-13T06:00:00.000+01:00",
    "DK1-Price": 54.74,
    "DK2-Price": 56.09
  },
  {
    "x": "2023-01-13T07:00:00.000+01:00",
    "DK1-Price": 87.88,
    "DK2-Price": 85.77
  },
  {
    "x": "2023-01-13T08:00:00.000+01:00",
    "DK1-Price": 105.95,
    "DK2-Price": 95.6
  },
  {
    "x": "2023-01-13T09:00:00.000+01:00",
    "DK1-Price": 100.64,
    "DK2-Price": 98.23
  },
  {
    "x": "2023-01-13T10:00:00.000+01:00",
    "DK1-Price": 94.85,
    "DK2-Price": 92.58
  },
  {
    "x": "2023-01-13T11:00:00.000+01:00",
    "DK1-Price": 84.93,
    "DK2-Price": 84.93
  },
  {
    "x": "2023-01-13T12:00:00.000+01:00",
    "DK1-Price": 76.53,
    "DK2-Price": 76.53
  },
  {
    "x": "2023-01-13T13:00:00.000+01:00",
    "DK1-Price": 70.24,
    "DK2-Price": 71.97
  },
  {
    "x": "2023-01-13T14:00:00.000+01:00",
    "DK1-Price": 73.55,
    "DK2-Price": 75.36
  },
  {
    "x": "2023-01-13T15:00:00.000+01:00",
    "DK1-Price": 79.85,
    "DK2-Price": 81.82
  },
  {
    "x": "2023-01-13T16:00:00.000+01:00",
    "DK1-Price": 85.31,
    "DK2-Price": 85.31
  },
  {
    "x": "2023-01-13T17:00:00.000+01:00",
    "DK1-Price": 96.9,
    "DK2-Price": 96.9
  },
  {
    "x": "2023-01-13T18:00:00.000+01:00",
    "DK1-Price": 96.97,
    "DK2-Price": 96.2
  },
  {
    "x": "2023-01-13T19:00:00.000+01:00",
    "DK1-Price": 95.91,
    "DK2-Price": 91.07
  },
  {
    "x": "2023-01-13T20:00:00.000+01:00",
    "DK1-Price": 84.94,
    "DK2-Price": 84.94
  },
  {
    "x": "2023-01-13T21:00:00.000+01:00",
    "DK1-Price": 76.89,
    "DK2-Price": 76.89
  },
  {
    "x": "2023-01-13T22:00:00.000+01:00",
    "DK1-Price": 76.51,
    "DK2-Price": 76.51
  },
  {
    "x": "2023-01-13T23:00:00.000+01:00",
    "DK1-Price": 68.3,
    "DK2-Price": 68.3
  },
  {
    "x": "2023-01-14T00:00:00.000+01:00",
    "DK1-Price": 25.68,
    "DK2-Price": 49.71
  },
  {
    "x": "2023-01-14T01:00:00.000+01:00",
    "DK1-Price": 34.62,
    "DK2-Price": 44.24
  },
  {
    "x": "2023-01-14T02:00:00.000+01:00",
    "DK1-Price": 44.7,
    "DK2-Price": 45.41
  },
  {
    "x": "2023-01-14T03:00:00.000+01:00",
    "DK1-Price": 41.23,
    "DK2-Price": 42.25
  },
  {
    "x": "2023-01-14T04:00:00.000+01:00",
    "DK1-Price": 40.7,
    "DK2-Price": 41.7
  },
  {
    "x": "2023-01-14T05:00:00.000+01:00",
    "DK1-Price": 40.68,
    "DK2-Price": 41.68
  },
  {
    "x": "2023-01-14T06:00:00.000+01:00",
    "DK1-Price": 45.1,
    "DK2-Price": 45.1
  },
  {
    "x": "2023-01-14T07:00:00.000+01:00",
    "DK1-Price": 53.4,
    "DK2-Price": 53.4
  },
  {
    "x": "2023-01-14T08:00:00.000+01:00",
    "DK1-Price": 53.63,
    "DK2-Price": 53.63
  },
  {
    "x": "2023-01-14T09:00:00.000+01:00",
    "DK1-Price": 56.89,
    "DK2-Price": 56.89
  },
  {
    "x": "2023-01-14T10:00:00.000+01:00",
    "DK1-Price": 66.72,
    "DK2-Price": 66.72
  },
  {
    "x": "2023-01-14T11:00:00.000+01:00",
    "DK1-Price": 65.56,
    "DK2-Price": 65.56
  },
  {
    "x": "2023-01-14T12:00:00.000+01:00",
    "DK1-Price": 65.39,
    "DK2-Price": 65.39
  },
  {
    "x": "2023-01-14T13:00:00.000+01:00",
    "DK1-Price": 62.69,
    "DK2-Price": 62.69
  },
  {
    "x": "2023-01-14T14:00:00.000+01:00",
    "DK1-Price": 42.15,
    "DK2-Price": 66.96
  },
  {
    "x": "2023-01-14T15:00:00.000+01:00",
    "DK1-Price": 19.92,
    "DK2-Price": 73.97
  },
  {
    "x": "2023-01-14T16:00:00.000+01:00",
    "DK1-Price": 9.04,
    "DK2-Price": 75.91
  },
  {
    "x": "2023-01-14T17:00:00.000+01:00",
    "DK1-Price": 11.04,
    "DK2-Price": 73.63
  },
  {
    "x": "2023-01-14T18:00:00.000+01:00",
    "DK1-Price": 13.69,
    "DK2-Price": 69.51
  },
  {
    "x": "2023-01-14T19:00:00.000+01:00",
    "DK1-Price": 6.84,
    "DK2-Price": 62.71
  },
  {
    "x": "2023-01-14T20:00:00.000+01:00",
    "DK1-Price": 9.03,
    "DK2-Price": 51.53
  },
  {
    "x": "2023-01-14T21:00:00.000+01:00",
    "DK1-Price": 9.07,
    "DK2-Price": 43.68
  },
  {
    "x": "2023-01-14T22:00:00.000+01:00",
    "DK1-Price": 5.9,
    "DK2-Price": 40.05
  },
  {
    "x": "2023-01-14T23:00:00.000+01:00",
    "DK1-Price": 5.19,
    "DK2-Price": 35.32
  },
  {
    "x": "2023-01-15T00:00:00.000+01:00",
    "DK1-Price": 3.94,
    "DK2-Price": 27.4
  },
  {
    "x": "2023-01-15T01:00:00.000+01:00",
    "DK1-Price": 1.71,
    "DK2-Price": 27.23
  },
  {
    "x": "2023-01-15T02:00:00.000+01:00",
    "DK1-Price": 4.1,
    "DK2-Price": 24.28
  },
  {
    "x": "2023-01-15T03:00:00.000+01:00",
    "DK1-Price": 2.65,
    "DK2-Price": 13
  },
  {
    "x": "2023-01-15T04:00:00.000+01:00",
    "DK1-Price": 2.87,
    "DK2-Price": 7.98
  },
  {
    "x": "2023-01-15T05:00:00.000+01:00",
    "DK1-Price": 4.01,
    "DK2-Price": 4.85
  },
  {
    "x": "2023-01-15T06:00:00.000+01:00",
    "DK1-Price": 1.58,
    "DK2-Price": 6.05
  },
  {
    "x": "2023-01-15T07:00:00.000+01:00",
    "DK1-Price": 1.74,
    "DK2-Price": 10.09
  },
  {
    "x": "2023-01-15T08:00:00.000+01:00",
    "DK1-Price": 9.08,
    "DK2-Price": 14.03
  },
  {
    "x": "2023-01-15T09:00:00.000+01:00",
    "DK1-Price": 10.31,
    "DK2-Price": 19.07
  },
  {
    "x": "2023-01-15T10:00:00.000+01:00",
    "DK1-Price": 9.01,
    "DK2-Price": 17.83
  },
  {
    "x": "2023-01-15T11:00:00.000+01:00",
    "DK1-Price": 8.03,
    "DK2-Price": 11.7
  },
  {
    "x": "2023-01-15T12:00:00.000+01:00",
    "DK1-Price": 6.76,
    "DK2-Price": 6.93
  },
  {
    "x": "2023-01-15T13:00:00.000+01:00",
    "DK1-Price": 0.42,
    "DK2-Price": 6.04
  },
  {
    "x": "2023-01-15T14:00:00.000+01:00",
    "DK1-Price": 0.29,
    "DK2-Price": 6.09
  },
  {
    "x": "2023-01-15T15:00:00.000+01:00",
    "DK1-Price": 0.82,
    "DK2-Price": 19.1
  },
  {
    "x": "2023-01-15T16:00:00.000+01:00",
    "DK1-Price": 13.69,
    "DK2-Price": 27.43
  },
  {
    "x": "2023-01-15T17:00:00.000+01:00",
    "DK1-Price": 30.9,
    "DK2-Price": 30.9
  },
  {
    "x": "2023-01-15T18:00:00.000+01:00",
    "DK1-Price": 26.95,
    "DK2-Price": 27.61
  },
  {
    "x": "2023-01-15T19:00:00.000+01:00",
    "DK1-Price": 25.27,
    "DK2-Price": 25.9
  },
  {
    "x": "2023-01-15T20:00:00.000+01:00",
    "DK1-Price": 12.17,
    "DK2-Price": 12.47
  },
  {
    "x": "2023-01-15T21:00:00.000+01:00",
    "DK1-Price": 19.69,
    "DK2-Price": 20.79
  },
  {
    "x": "2023-01-15T22:00:00.000+01:00",
    "DK1-Price": 32.14,
    "DK2-Price": 31.04
  },
  {
    "x": "2023-01-15T23:00:00.000+01:00",
    "DK1-Price": 37.47,
    "DK2-Price": 32.38
  },
  {
    "x": "2023-01-16T00:00:00.000+01:00",
    "DK1-Price": 60.01,
    "DK2-Price": 35.35
  },
  {
    "x": "2023-01-16T01:00:00.000+01:00",
    "DK1-Price": 60.01,
    "DK2-Price": 36.13
  },
  {
    "x": "2023-01-16T02:00:00.000+01:00",
    "DK1-Price": 62.72,
    "DK2-Price": 36.13
  },
  {
    "x": "2023-01-16T03:00:00.000+01:00",
    "DK1-Price": 56.1,
    "DK2-Price": 38.57
  },
  {
    "x": "2023-01-16T04:00:00.000+01:00",
    "DK1-Price": 63.3,
    "DK2-Price": 41.81
  },
  {
    "x": "2023-01-16T05:00:00.000+01:00",
    "DK1-Price": 87,
    "DK2-Price": 45.59
  },
  {
    "x": "2023-01-16T06:00:00.000+01:00",
    "DK1-Price": 154.63,
    "DK2-Price": 66.81
  },
  {
    "x": "2023-01-16T07:00:00.000+01:00",
    "DK1-Price": 175.11,
    "DK2-Price": 86.63
  },
  {
    "x": "2023-01-16T08:00:00.000+01:00",
    "DK1-Price": 185.99,
    "DK2-Price": 154.9
  },
  {
    "x": "2023-01-16T09:00:00.000+01:00",
    "DK1-Price": 170,
    "DK2-Price": 161.02
  },
  {
    "x": "2023-01-16T10:00:00.000+01:00",
    "DK1-Price": 150.2,
    "DK2-Price": 150.2
  },
  {
    "x": "2023-01-16T11:00:00.000+01:00",
    "DK1-Price": 150.89,
    "DK2-Price": 150.89
  },
  {
    "x": "2023-01-16T12:00:00.000+01:00",
    "DK1-Price": 147.04,
    "DK2-Price": 147.04
  },
  {
    "x": "2023-01-16T13:00:00.000+01:00",
    "DK1-Price": 140.87,
    "DK2-Price": 110.04
  },
  {
    "x": "2023-01-16T14:00:00.000+01:00",
    "DK1-Price": 141.24,
    "DK2-Price": 137.85
  },
  {
    "x": "2023-01-16T15:00:00.000+01:00",
    "DK1-Price": 145.69,
    "DK2-Price": 141.17
  },
  {
    "x": "2023-01-16T16:00:00.000+01:00",
    "DK1-Price": 150.81,
    "DK2-Price": 146.14
  },
  {
    "x": "2023-01-16T17:00:00.000+01:00",
    "DK1-Price": 166.79,
    "DK2-Price": 129.91
  },
  {
    "x": "2023-01-16T18:00:00.000+01:00",
    "DK1-Price": 173.72,
    "DK2-Price": 88.91
  },
  {
    "x": "2023-01-16T19:00:00.000+01:00",
    "DK1-Price": 150.5,
    "DK2-Price": 80.04
  },
  {
    "x": "2023-01-16T20:00:00.000+01:00",
    "DK1-Price": 136.97,
    "DK2-Price": 65.91
  },
  {
    "x": "2023-01-16T21:00:00.000+01:00",
    "DK1-Price": 127.74,
    "DK2-Price": 59.69
  },
  {
    "x": "2023-01-16T22:00:00.000+01:00",
    "DK1-Price": 123.24,
    "DK2-Price": 51.24
  },
  {
    "x": "2023-01-16T23:00:00.000+01:00",
    "DK1-Price": 109.4,
    "DK2-Price": 46.52
  },
  {
    "x": "2023-01-17T00:00:00.000+01:00",
    "DK1-Price": 98.24,
    "DK2-Price": 47.13
  },
  {
    "x": "2023-01-17T01:00:00.000+01:00",
    "DK1-Price": 94.61,
    "DK2-Price": 42.94
  },
  {
    "x": "2023-01-17T02:00:00.000+01:00",
    "DK1-Price": 91.91,
    "DK2-Price": 42.15
  },
  {
    "x": "2023-01-17T03:00:00.000+01:00",
    "DK1-Price": 89.51,
    "DK2-Price": 40.8
  },
  {
    "x": "2023-01-17T04:00:00.000+01:00",
    "DK1-Price": 91.77,
    "DK2-Price": 41.62
  },
  {
    "x": "2023-01-17T05:00:00.000+01:00",
    "DK1-Price": 100,
    "DK2-Price": 45.75
  },
  {
    "x": "2023-01-17T06:00:00.000+01:00",
    "DK1-Price": 116.96,
    "DK2-Price": 60.17
  },
  {
    "x": "2023-01-17T07:00:00.000+01:00",
    "DK1-Price": 140.8,
    "DK2-Price": 70.87
  },
  {
    "x": "2023-01-17T08:00:00.000+01:00",
    "DK1-Price": 151.96,
    "DK2-Price": 73.37
  },
  {
    "x": "2023-01-17T09:00:00.000+01:00",
    "DK1-Price": 136.1,
    "DK2-Price": 72.62
  },
  {
    "x": "2023-01-17T10:00:00.000+01:00",
    "DK1-Price": 126.17,
    "DK2-Price": 73.95
  },
  {
    "x": "2023-01-17T11:00:00.000+01:00",
    "DK1-Price": 122.75,
    "DK2-Price": 76.15
  },
  {
    "x": "2023-01-17T12:00:00.000+01:00",
    "DK1-Price": 116.07,
    "DK2-Price": 79.96
  },
  {
    "x": "2023-01-17T13:00:00.000+01:00",
    "DK1-Price": 129.38,
    "DK2-Price": 75.11
  },
  {
    "x": "2023-01-17T14:00:00.000+01:00",
    "DK1-Price": 128.88,
    "DK2-Price": 72.21
  },
  {
    "x": "2023-01-17T15:00:00.000+01:00",
    "DK1-Price": 137.5,
    "DK2-Price": 75.57
  },
  {
    "x": "2023-01-17T16:00:00.000+01:00",
    "DK1-Price": 159.86,
    "DK2-Price": 76.03
  },
  {
    "x": "2023-01-17T17:00:00.000+01:00",
    "DK1-Price": 156.43,
    "DK2-Price": 76.56
  },
  {
    "x": "2023-01-17T18:00:00.000+01:00",
    "DK1-Price": 152,
    "DK2-Price": 73.46
  },
  {
    "x": "2023-01-17T19:00:00.000+01:00",
    "DK1-Price": 145.4,
    "DK2-Price": 67.19
  },
  {
    "x": "2023-01-17T20:00:00.000+01:00",
    "DK1-Price": 139.3,
    "DK2-Price": 60.14
  },
  {
    "x": "2023-01-17T21:00:00.000+01:00",
    "DK1-Price": 136.15,
    "DK2-Price": 53.73
  },
  {
    "x": "2023-01-17T22:00:00.000+01:00",
    "DK1-Price": 128.55,
    "DK2-Price": 47.42
  },
  {
    "x": "2023-01-17T23:00:00.000+01:00",
    "DK1-Price": 124.32,
    "DK2-Price": 43.34
  },
  {
    "x": "2023-01-18T00:00:00.000+01:00",
    "DK1-Price": 119.04,
    "DK2-Price": 39.85
  },
  {
    "x": "2023-01-18T01:00:00.000+01:00",
    "DK1-Price": 118.07,
    "DK2-Price": 38.74
  },
  {
    "x": "2023-01-18T02:00:00.000+01:00",
    "DK1-Price": 119.21,
    "DK2-Price": 38.69
  },
  {
    "x": "2023-01-18T03:00:00.000+01:00",
    "DK1-Price": 118.93,
    "DK2-Price": 38.32
  },
  {
    "x": "2023-01-18T04:00:00.000+01:00",
    "DK1-Price": 116.19,
    "DK2-Price": 42.7
  },
  {
    "x": "2023-01-18T05:00:00.000+01:00",
    "DK1-Price": 121.91,
    "DK2-Price": 52.07
  },
  {
    "x": "2023-01-18T06:00:00.000+01:00",
    "DK1-Price": 130.39,
    "DK2-Price": 130.39
  },
  {
    "x": "2023-01-18T07:00:00.000+01:00",
    "DK1-Price": 166.4,
    "DK2-Price": 166.4
  },
  {
    "x": "2023-01-18T08:00:00.000+01:00",
    "DK1-Price": 181.5,
    "DK2-Price": 181.5
  },
  {
    "x": "2023-01-18T09:00:00.000+01:00",
    "DK1-Price": 176.56,
    "DK2-Price": 176.56
  },
  {
    "x": "2023-01-18T10:00:00.000+01:00",
    "DK1-Price": 140,
    "DK2-Price": 140
  },
  {
    "x": "2023-01-18T11:00:00.000+01:00",
    "DK1-Price": 130.36,
    "DK2-Price": 130.36
  },
  {
    "x": "2023-01-18T12:00:00.000+01:00",
    "DK1-Price": 122.94,
    "DK2-Price": 122.94
  },
  {
    "x": "2023-01-18T13:00:00.000+01:00",
    "DK1-Price": 120,
    "DK2-Price": 120
  },
  {
    "x": "2023-01-18T14:00:00.000+01:00",
    "DK1-Price": 123.66,
    "DK2-Price": 123.66
  },
  {
    "x": "2023-01-18T15:00:00.000+01:00",
    "DK1-Price": 140,
    "DK2-Price": 140
  },
  {
    "x": "2023-01-18T16:00:00.000+01:00",
    "DK1-Price": 147.97,
    "DK2-Price": 150.11
  },
  {
    "x": "2023-01-18T17:00:00.000+01:00",
    "DK1-Price": 160,
    "DK2-Price": 160.69
  },
  {
    "x": "2023-01-18T18:00:00.000+01:00",
    "DK1-Price": 137.48,
    "DK2-Price": 155.15
  },
  {
    "x": "2023-01-18T19:00:00.000+01:00",
    "DK1-Price": 130.34,
    "DK2-Price": 130.34
  },
  {
    "x": "2023-01-18T20:00:00.000+01:00",
    "DK1-Price": 120.97,
    "DK2-Price": 120.97
  },
  {
    "x": "2023-01-18T21:00:00.000+01:00",
    "DK1-Price": 119.9,
    "DK2-Price": 119.9
  },
  {
    "x": "2023-01-18T22:00:00.000+01:00",
    "DK1-Price": 117.51,
    "DK2-Price": 117.51
  },
  {
    "x": "2023-01-18T23:00:00.000+01:00",
    "DK1-Price": 111.46,
    "DK2-Price": 111.46
  },
  {
    "x": "2023-01-19T00:00:00.000+01:00",
    "DK1-Price": 111.53,
    "DK2-Price": 83.56
  },
  {
    "x": "2023-01-19T01:00:00.000+01:00",
    "DK1-Price": 106.98,
    "DK2-Price": 83.08
  },
  {
    "x": "2023-01-19T02:00:00.000+01:00",
    "DK1-Price": 104.97,
    "DK2-Price": 82.7
  },
  {
    "x": "2023-01-19T03:00:00.000+01:00",
    "DK1-Price": 101.72,
    "DK2-Price": 84.92
  },
  {
    "x": "2023-01-19T04:00:00.000+01:00",
    "DK1-Price": 99.14,
    "DK2-Price": 92.84
  },
  {
    "x": "2023-01-19T05:00:00.000+01:00",
    "DK1-Price": 110.95,
    "DK2-Price": 104.96
  },
  {
    "x": "2023-01-19T06:00:00.000+01:00",
    "DK1-Price": 118.22,
    "DK2-Price": 118.22
  },
  {
    "x": "2023-01-19T07:00:00.000+01:00",
    "DK1-Price": 149.62,
    "DK2-Price": 149.62
  },
  {
    "x": "2023-01-19T08:00:00.000+01:00",
    "DK1-Price": 159.93,
    "DK2-Price": 159.93
  },
  {
    "x": "2023-01-19T09:00:00.000+01:00",
    "DK1-Price": 155.88,
    "DK2-Price": 155.88
  },
  {
    "x": "2023-01-19T10:00:00.000+01:00",
    "DK1-Price": 154.81,
    "DK2-Price": 154.81
  },
  {
    "x": "2023-01-19T11:00:00.000+01:00",
    "DK1-Price": 138.63,
    "DK2-Price": 138.63
  },
  {
    "x": "2023-01-19T12:00:00.000+01:00",
    "DK1-Price": 150.07,
    "DK2-Price": 146.47
  },
  {
    "x": "2023-01-19T13:00:00.000+01:00",
    "DK1-Price": 154.87,
    "DK2-Price": 151.16
  },
  {
    "x": "2023-01-19T14:00:00.000+01:00",
    "DK1-Price": 160.49,
    "DK2-Price": 155.35
  },
  {
    "x": "2023-01-19T15:00:00.000+01:00",
    "DK1-Price": 175.96,
    "DK2-Price": 170.33
  },
  {
    "x": "2023-01-19T16:00:00.000+01:00",
    "DK1-Price": 186.29,
    "DK2-Price": 180.33
  },
  {
    "x": "2023-01-19T17:00:00.000+01:00",
    "DK1-Price": 198.73,
    "DK2-Price": 173.75
  },
  {
    "x": "2023-01-19T18:00:00.000+01:00",
    "DK1-Price": 197.57,
    "DK2-Price": 156.61
  },
  {
    "x": "2023-01-19T19:00:00.000+01:00",
    "DK1-Price": 171.43,
    "DK2-Price": 151.55
  },
  {
    "x": "2023-01-19T20:00:00.000+01:00",
    "DK1-Price": 150,
    "DK2-Price": 145.65
  },
  {
    "x": "2023-01-19T21:00:00.000+01:00",
    "DK1-Price": 148.41,
    "DK2-Price": 143.66
  },
  {
    "x": "2023-01-19T22:00:00.000+01:00",
    "DK1-Price": 149.34,
    "DK2-Price": 119
  },
  {
    "x": "2023-01-19T23:00:00.000+01:00",
    "DK1-Price": 139,
    "DK2-Price": 106.21
  },
  {
    "x": "2023-01-20T00:00:00.000+01:00",
    "DK1-Price": 146.89,
    "DK2-Price": 146.89
  },
  {
    "x": "2023-01-20T01:00:00.000+01:00",
    "DK1-Price": 144.5,
    "DK2-Price": 144.5
  },
  {
    "x": "2023-01-20T02:00:00.000+01:00",
    "DK1-Price": 142.44,
    "DK2-Price": 142.44
  },
  {
    "x": "2023-01-20T03:00:00.000+01:00",
    "DK1-Price": 142.8,
    "DK2-Price": 142.8
  },
  {
    "x": "2023-01-20T04:00:00.000+01:00",
    "DK1-Price": 144.98,
    "DK2-Price": 144.98
  },
  {
    "x": "2023-01-20T05:00:00.000+01:00",
    "DK1-Price": 150.5,
    "DK2-Price": 150.5
  },
  {
    "x": "2023-01-20T06:00:00.000+01:00",
    "DK1-Price": 176.01,
    "DK2-Price": 176.01
  },
  {
    "x": "2023-01-20T07:00:00.000+01:00",
    "DK1-Price": 208.07,
    "DK2-Price": 208.07
  },
  {
    "x": "2023-01-20T08:00:00.000+01:00",
    "DK1-Price": 235.06,
    "DK2-Price": 235.06
  },
  {
    "x": "2023-01-20T09:00:00.000+01:00",
    "DK1-Price": 221.7,
    "DK2-Price": 221.7
  },
  {
    "x": "2023-01-20T10:00:00.000+01:00",
    "DK1-Price": 209.77,
    "DK2-Price": 209.77
  },
  {
    "x": "2023-01-20T11:00:00.000+01:00",
    "DK1-Price": 201.52,
    "DK2-Price": 201.52
  },
  {
    "x": "2023-01-20T12:00:00.000+01:00",
    "DK1-Price": 189.26,
    "DK2-Price": 189.26
  },
  {
    "x": "2023-01-20T13:00:00.000+01:00",
    "DK1-Price": 181.63,
    "DK2-Price": 181.63
  },
  {
    "x": "2023-01-20T14:00:00.000+01:00",
    "DK1-Price": 182.36,
    "DK2-Price": 182.36
  },
  {
    "x": "2023-01-20T15:00:00.000+01:00",
    "DK1-Price": 192,
    "DK2-Price": 192
  },
  {
    "x": "2023-01-20T16:00:00.000+01:00",
    "DK1-Price": 200,
    "DK2-Price": 200
  },
  {
    "x": "2023-01-20T17:00:00.000+01:00",
    "DK1-Price": 208.22,
    "DK2-Price": 208.22
  },
  {
    "x": "2023-01-20T18:00:00.000+01:00",
    "DK1-Price": 208.4,
    "DK2-Price": 208.4
  },
  {
    "x": "2023-01-20T19:00:00.000+01:00",
    "DK1-Price": 197,
    "DK2-Price": 197
  },
  {
    "x": "2023-01-20T20:00:00.000+01:00",
    "DK1-Price": 175.7,
    "DK2-Price": 175.7
  },
  {
    "x": "2023-01-20T21:00:00.000+01:00",
    "DK1-Price": 166.37,
    "DK2-Price": 166.37
  },
  {
    "x": "2023-01-20T22:00:00.000+01:00",
    "DK1-Price": 163.1,
    "DK2-Price": 163.1
  },
  {
    "x": "2023-01-20T23:00:00.000+01:00",
    "DK1-Price": 147.55,
    "DK2-Price": 147.55
  },
  {
    "x": "2023-01-21T00:00:00.000+01:00",
    "DK1-Price": null,
    "DK2-Price": null
  },
  {
    "x": "2023-01-21T01:00:00.000+01:00",
    "DK1-Price": null,
    "DK2-Price": null
  },
  {
    "x": "2023-01-21T02:00:00.000+01:00",
    "DK1-Price": null,
    "DK2-Price": null
  },
  {
    "x": "2023-01-21T03:00:00.000+01:00",
    "DK1-Price": null,
    "DK2-Price": null
  },
  {
    "x": "2023-01-21T04:00:00.000+01:00",
    "DK1-Price": null,
    "DK2-Price": null
  },
  {
    "x": "2023-01-21T05:00:00.000+01:00",
    "DK1-Price": null,
    "DK2-Price": null
  },
  {
    "x": "2023-01-21T06:00:00.000+01:00",
    "DK1-Price": null,
    "DK2-Price": null
  },
  {
    "x": "2023-01-21T07:00:00.000+01:00",
    "DK1-Price": null,
    "DK2-Price": null
  },
  {
    "x": "2023-01-21T08:00:00.000+01:00",
    "DK1-Price": null,
    "DK2-Price": null
  },
  {
    "x": "2023-01-21T09:00:00.000+01:00",
    "DK1-Price": null,
    "DK2-Price": null
  },
  {
    "x": "2023-01-21T10:00:00.000+01:00",
    "DK1-Price": null,
    "DK2-Price": null
  },
  {
    "x": "2023-01-21T11:00:00.000+01:00",
    "DK1-Price": null,
    "DK2-Price": null
  },
  {
    "x": "2023-01-21T12:00:00.000+01:00",
    "DK1-Price": null,
    "DK2-Price": null
  },
  {
    "x": "2023-01-21T13:00:00.000+01:00",
    "DK1-Price": null,
    "DK2-Price": null
  },
  {
    "x": "2023-01-21T14:00:00.000+01:00",
    "DK1-Price": null,
    "DK2-Price": null
  },
  {
    "x": "2023-01-21T15:00:00.000+01:00",
    "DK1-Price": null,
    "DK2-Price": null
  },
  {
    "x": "2023-01-21T16:00:00.000+01:00",
    "DK1-Price": null,
    "DK2-Price": null
  },
  {
    "x": "2023-01-21T17:00:00.000+01:00",
    "DK1-Price": null,
    "DK2-Price": null
  },
  {
    "x": "2023-01-21T18:00:00.000+01:00",
    "DK1-Price": null,
    "DK2-Price": null
  },
  {
    "x": "2023-01-21T19:00:00.000+01:00",
    "DK1-Price": null,
    "DK2-Price": null
  },
  {
    "x": "2023-01-21T20:00:00.000+01:00",
    "DK1-Price": null,
    "DK2-Price": null
  },
  {
    "x": "2023-01-21T21:00:00.000+01:00",
    "DK1-Price": null,
    "DK2-Price": null
  },
  {
    "x": "2023-01-21T22:00:00.000+01:00",
    "DK1-Price": null,
    "DK2-Price": null
  },
  {
    "x": "2023-01-21T23:00:00.000+01:00",
    "DK1-Price": null,
    "DK2-Price": null
  }
]