[
  {
    "x": "2024-01-01T00:00:00.000+01:00",
    "PT-Cross border electricity trading": 2069.1,
    "PT-Biomass": 361.8,
    "PT-Others": 29.7,
    "PT-Solar": 0,
    "PT-Load": 5423.4,
    "PT-Residual load": 5070.2,
    "PT-Renewable share of generation": 49.1,
    "PT-Renewable share of load": 29.8,
    "PT-undefined": 63.33,
    "PT-Hydro Pumped": 1454.3,
    "PT-Wind": 353.20000000000005,
    "PT-Coal": null,
    "PT-Hydro": 2356.3,
    "PT-Import": null,
    "PT-Gas": 190.7
  },
  {
    "x": "2024-01-01T01:00:00.000+01:00",
    "PT-Cross border electricity trading": 2368.3,
    "PT-Biomass": 364.1,
    "PT-Others": 29.7,
    "PT-Solar": 0,
    "PT-Load": 5129.8,
    "PT-Residual load": 4786.5,
    "PT-Renewable share of generation": 53.5,
    "PT-Renewable share of load": 28.9,
    "PT-undefined": 50.09,
    "PT-Hydro Pumped": 1063.8,
    "PT-Wind": 343.3,
    "PT-Coal": null,
    "PT-Hydro": 1839.7999999999997,
    "PT-Import": null,
    "PT-Gas": 192.6
  },
  {
    "x": "2024-01-01T02:00:00.000+01:00",
    "PT-Cross border electricity trading": 2970,
    "PT-Biomass": 366.2,
    "PT-Others": 30.2,
    "PT-Solar": 0,
    "PT-Load": 4957.5,
    "PT-Residual load": 4543.2,
    "PT-Renewable share of generation": 66.9,
    "PT-Renewable share of load": 28.7,
    "PT-undefined": 47.5,
    "PT-Hydro Pumped": 407.3,
    "PT-Wind": 414.3,
    "PT-Coal": null,
    "PT-Hydro": 1050.7,
    "PT-Import": null,
    "PT-Gas": 189.9
  },
  {
    "x": "2024-01-01T03:00:00.000+01:00",
    "PT-Cross border electricity trading": 2560.1,
    "PT-Biomass": 364.8,
    "PT-Others": 30.1,
    "PT-Solar": 0,
    "PT-Load": 4678.7,
    "PT-Residual load": 4190.7,
    "PT-Renewable share of generation": 81.7,
    "PT-Renewable share of load": 44.7,
    "PT-undefined": 43.5,
    "PT-Hydro Pumped": -254.10000000000002,
    "PT-Wind": 488,
    "PT-Coal": null,
    "PT-Hydro": 984.9000000000001,
    "PT-Import": null,
    "PT-Gas": 189.6
  },
  {
    "x": "2024-01-01T04:00:00.000+01:00",
    "PT-Cross border electricity trading": 2815.9,
    "PT-Biomass": 365.4,
    "PT-Others": 30.2,
    "PT-Solar": 0,
    "PT-Load": 4408.1,
    "PT-Residual load": 3896.3,
    "PT-Renewable share of generation": 78.8,
    "PT-Renewable share of load": 41,
    "PT-undefined": 42.5,
    "PT-Hydro Pumped": -427.5,
    "PT-Wind": 511.8,
    "PT-Coal": null,
    "PT-Hydro": 502.70000000000005,
    "PT-Import": null,
    "PT-Gas": 189.8
  },
  {
    "x": "2024-01-01T05:00:00.000+01:00",
    "PT-Cross border electricity trading": 2835,
    "PT-Biomass": 364,
    "PT-Others": 30.2,
    "PT-Solar": 0,
    "PT-Load": 4241.8,
    "PT-Residual load": 3703,
    "PT-Renewable share of generation": 79.7,
    "PT-Renewable share of load": 44.1,
    "PT-undefined": 42.09,
    "PT-Hydro Pumped": -630.1,
    "PT-Wind": 538.8,
    "PT-Coal": null,
    "PT-Hydro": 335.70000000000005,
    "PT-Import": null,
    "PT-Gas": 190.1
  },
  {
    "x": "2024-01-01T06:00:00.000+01:00",
    "PT-Cross border electricity trading": 2835,
    "PT-Biomass": 364.6,
    "PT-Others": 30.2,
    "PT-Solar": 0,
    "PT-Load": 4165.8,
    "PT-Residual load": 3605,
    "PT-Renewable share of generation": 79.1,
    "PT-Renewable share of load": 45.7,
    "PT-undefined": 42.5,
    "PT-Hydro Pumped": -747.2,
    "PT-Wind": 560.8000000000001,
    "PT-Coal": null,
    "PT-Hydro": 230.29999999999995,
    "PT-Import": null,
    "PT-Gas": 190.1
  },
  {
    "x": "2024-01-01T07:00:00.000+01:00",
    "PT-Cross border electricity trading": 2880,
    "PT-Biomass": 362.8,
    "PT-Others": 30.9,
    "PT-Solar": 0,
    "PT-Load": 4154.4,
    "PT-Residual load": 3705.9,
    "PT-Renewable share of generation": 71.4,
    "PT-Renewable share of load": 33.7,
    "PT-undefined": 42.59,
    "PT-Hydro Pumped": -348.4,
    "PT-Wind": 448.5,
    "PT-Coal": null,
    "PT-Hydro": 241.20000000000005,
    "PT-Import": null,
    "PT-Gas": 190.9
  },
  {
    "x": "2024-01-01T08:00:00.000+01:00",
    "PT-Cross border electricity trading": 2846.4,
    "PT-Biomass": 364.5,
    "PT-Others": 30.6,
    "PT-Solar": 0.8,
    "PT-Load": 4125.6,
    "PT-Residual load": 3783.8,
    "PT-Renewable share of generation": 72.5,
    "PT-Renewable share of load": 32.1,
    "PT-undefined": 43.37,
    "PT-Hydro Pumped": -293.9,
    "PT-Wind": 341,
    "PT-Coal": null,
    "PT-Hydro": 324.6,
    "PT-Import": null,
    "PT-Gas": 192.2
  },
  {
    "x": "2024-01-01T09:00:00.000+01:00",
    "PT-Cross border electricity trading": 2880,
    "PT-Biomass": 362.6,
    "PT-Others": 29.8,
    "PT-Solar": 119.9,
    "PT-Load": 4156.5,
    "PT-Residual load": 3706.8,
    "PT-Renewable share of generation": 67.2,
    "PT-Renewable share of load": 32.1,
    "PT-undefined": 42.29,
    "PT-Hydro Pumped": -229.39999999999998,
    "PT-Wind": 329.8,
    "PT-Coal": null,
    "PT-Hydro": 292.90000000000003,
    "PT-Import": null,
    "PT-Gas": 195.1
  },
  {
    "x": "2024-01-01T10:00:00.000+01:00",
    "PT-Cross border electricity trading": 2880,
    "PT-Biomass": 359.5,
    "PT-Others": 28.9,
    "PT-Solar": 539.4,
    "PT-Load": 4397.6,
    "PT-Residual load": 3562.8,
    "PT-Renewable share of generation": 78.1,
    "PT-Renewable share of load": 40.2,
    "PT-undefined": 35.61,
    "PT-Hydro Pumped": -462.79999999999995,
    "PT-Wind": 295.40000000000003,
    "PT-Coal": null,
    "PT-Hydro": 110.00000000000006,
    "PT-Import": null,
    "PT-Gas": 198.8
  },
  {
    "x": "2024-01-01T11:00:00.000+01:00",
    "PT-Cross border electricity trading": 2880,
    "PT-Biomass": 361.5,
    "PT-Others": 30.4,
    "PT-Solar": 1011.3,
    "PT-Load": 4715.3,
    "PT-Residual load": 3394,
    "PT-Renewable share of generation": 83,
    "PT-Renewable share of load": 46.8,
    "PT-undefined": 29.8,
    "PT-Hydro Pumped": -624,
    "PT-Wind": 310,
    "PT-Coal": null,
    "PT-Hydro": -98.89999999999998,
    "PT-Import": null,
    "PT-Gas": 197.1
  },
  {
    "x": "2024-01-01T12:00:00.000+01:00",
    "PT-Cross border electricity trading": 4095,
    "PT-Biomass": 363.3,
    "PT-Others": 30.2,
    "PT-Solar": 1243.5,
    "PT-Load": 5086.9,
    "PT-Residual load": 3428.9,
    "PT-Renewable share of generation": 86.7,
    "PT-Renewable share of load": 50.7,
    "PT-undefined": 3.2,
    "PT-Hydro Pumped": -1809.1,
    "PT-Wind": 414.5,
    "PT-Coal": null,
    "PT-Hydro": -1253.7999999999997,
    "PT-Import": null,
    "PT-Gas": 196.9
  },
  {
    "x": "2024-01-01T13:00:00.000+01:00",
    "PT-Cross border electricity trading": 4095,
    "PT-Biomass": 363.8,
    "PT-Others": 30.2,
    "PT-Solar": 1272.8,
    "PT-Load": 5324.6,
    "PT-Residual load": 3518.8,
    "PT-Renewable share of generation": 90.8,
    "PT-Renewable share of load": 50.8,
    "PT-undefined": 2.06,
    "PT-Hydro Pumped": -1656.8999999999999,
    "PT-Wind": 533,
    "PT-Coal": null,
    "PT-Hydro": -1123.8,
    "PT-Import": null,
    "PT-Gas": 195.5
  },
  {
    "x": "2024-01-01T14:00:00.000+01:00",
    "PT-Cross border electricity trading": 4095,
    "PT-Biomass": 365.1,
    "PT-Others": 29.9,
    "PT-Solar": 1171.2,
    "PT-Load": 5152.4,
    "PT-Residual load": 3355.1,
    "PT-Renewable share of generation": 91.7,
    "PT-Renewable share of load": 52.5,
    "PT-undefined": 1.73,
    "PT-Hydro Pumped": -1830.1999999999998,
    "PT-Wind": 626.0999999999999,
    "PT-Coal": null,
    "PT-Hydro": -1286.2999999999997,
    "PT-Import": null,
    "PT-Gas": 196.2
  },
  {
    "x": "2024-01-01T15:00:00.000+01:00",
    "PT-Cross border electricity trading": 3566.8,
    "PT-Biomass": 367.3,
    "PT-Others": 30.7,
    "PT-Solar": 895,
    "PT-Load": 4985,
    "PT-Residual load": 3430,
    "PT-Renewable share of generation": 91.7,
    "PT-Renewable share of load": 50.1,
    "PT-undefined": 5.72,
    "PT-Hydro Pumped": -1357.9,
    "PT-Wind": 660,
    "PT-Coal": null,
    "PT-Hydro": -780.7,
    "PT-Import": null,
    "PT-Gas": 195.7
  },
  {
    "x": "2024-01-01T16:00:00.000+01:00",
    "PT-Cross border electricity trading": 3154.2,
    "PT-Biomass": 363.4,
    "PT-Others": 29.9,
    "PT-Solar": 589.5,
    "PT-Load": 5074.7,
    "PT-Residual load": 3767.1,
    "PT-Renewable share of generation": 90.1,
    "PT-Renewable share of load": 44.8,
    "PT-undefined": 18.49,
    "PT-Hydro Pumped": -703.7,
    "PT-Wind": 718.1,
    "PT-Coal": null,
    "PT-Hydro": -102.00000000000006,
    "PT-Import": null,
    "PT-Gas": 193.4
  },
  {
    "x": "2024-01-01T17:00:00.000+01:00",
    "PT-Cross border electricity trading": 3588.5,
    "PT-Biomass": 364.1,
    "PT-Others": 30.3,
    "PT-Solar": 158.1,
    "PT-Load": 5323.2,
    "PT-Residual load": 4445.4,
    "PT-Renewable share of generation": 77.6,
    "PT-Renewable share of load": 36,
    "PT-undefined": 37,
    "PT-Hydro Pumped": -305.9,
    "PT-Wind": 719.7,
    "PT-Coal": null,
    "PT-Hydro": 369.4,
    "PT-Import": null,
    "PT-Gas": 194.2
  },
  {
    "x": "2024-01-01T18:00:00.000+01:00",
    "PT-Cross border electricity trading": 2070.7,
    "PT-Biomass": 363.7,
    "PT-Others": 30.4,
    "PT-Solar": 4,
    "PT-Load": 5899.7,
    "PT-Residual load": 5118.9,
    "PT-Renewable share of generation": 53.6,
    "PT-Renewable share of load": 35.1,
    "PT-undefined": 47.5,
    "PT-Hydro Pumped": 1348.2,
    "PT-Wind": 776.8000000000001,
    "PT-Coal": null,
    "PT-Hydro": 2273.7,
    "PT-Import": null,
    "PT-Gas": 194.9
  },
  {
    "x": "2024-01-01T19:00:00.000+01:00",
    "PT-Cross border electricity trading": 1814.1,
    "PT-Biomass": 362,
    "PT-Others": 30.8,
    "PT-Solar": 0,
    "PT-Load": 6438.5,
    "PT-Residual load": 5398.8,
    "PT-Renewable share of generation": 57.5,
    "PT-Renewable share of load": 41.6,
    "PT-undefined": 54.97,
    "PT-Hydro Pumped": 1754.1,
    "PT-Wind": 1039.7,
    "PT-Coal": null,
    "PT-Hydro": 3033.7,
    "PT-Import": null,
    "PT-Gas": 195.3
  },
  {
    "x": "2024-01-01T20:00:00.000+01:00",
    "PT-Cross border electricity trading": 1384.1,
    "PT-Biomass": 352.8,
    "PT-Others": 30.8,
    "PT-Solar": 0,
    "PT-Load": 6669.2,
    "PT-Residual load": 5070.4,
    "PT-Renewable share of generation": 58.2,
    "PT-Renewable share of load": 47.1,
    "PT-undefined": 60.9,
    "PT-Hydro Pumped": 2033.3,
    "PT-Wind": 1598.8,
    "PT-Coal": null,
    "PT-Hydro": 3225.8999999999996,
    "PT-Import": null,
    "PT-Gas": 195.1
  },
  {
    "x": "2024-01-01T21:00:00.000+01:00",
    "PT-Cross border electricity trading": 1049.3,
    "PT-Biomass": 351.5,
    "PT-Others": 30.5,
    "PT-Solar": 0,
    "PT-Load": 6670,
    "PT-Residual load": 4620.5,
    "PT-Renewable share of generation": 65.4,
    "PT-Renewable share of load": 52.9,
    "PT-undefined": 60,
    "PT-Hydro Pumped": 1639.5,
    "PT-Wind": 2049.5,
    "PT-Coal": null,
    "PT-Hydro": 2764.1,
    "PT-Import": null,
    "PT-Gas": 195.3
  },
  {
    "x": "2024-01-01T22:00:00.000+01:00",
    "PT-Cross border electricity trading": 1593.2,
    "PT-Biomass": 354.9,
    "PT-Others": 30.9,
    "PT-Solar": 0,
    "PT-Load": 6390.2,
    "PT-Residual load": 4657.5,
    "PT-Renewable share of generation": 65.1,
    "PT-Renewable share of load": 48.2,
    "PT-undefined": 47.5,
    "PT-Hydro Pumped": 1425.3,
    "PT-Wind": 1732.7,
    "PT-Coal": null,
    "PT-Hydro": 2416.3,
    "PT-Import": null,
    "PT-Gas": 194.9
  },
  {
    "x": "2024-01-01T23:00:00.000+01:00",
    "PT-Cross border electricity trading": 2835,
    "PT-Biomass": 351.3,
    "PT-Others": 30.6,
    "PT-Solar": 0,
    "PT-Load": 5982.5,
    "PT-Residual load": 3920.7,
    "PT-Renewable share of generation": 84.2,
    "PT-Renewable share of load": 50.5,
    "PT-undefined": 42.09,
    "PT-Hydro Pumped": -7.399999999999977,
    "PT-Wind": 2061.8,
    "PT-Coal": null,
    "PT-Hydro": 598.1,
    "PT-Import": null,
    "PT-Gas": 193.7
  },
  {
    "x": "2024-01-02T00:00:00.000+01:00",
    "PT-Cross border electricity trading": 2375,
    "PT-Biomass": 350.8,
    "PT-Others": 30.2,
    "PT-Solar": 0,
    "PT-Load": 5399.1,
    "PT-Residual load": 2918,
    "PT-Renewable share of generation": 88.7,
    "PT-Renewable share of load": 63.8,
    "PT-undefined": 37.8,
    "PT-Hydro Pumped": -755.5,
    "PT-Wind": 2481.1,
    "PT-Coal": null,
    "PT-Hydro": -141.79999999999995,
    "PT-Import": null,
    "PT-Gas": 193.6
  },
  {
    "x": "2024-01-02T01:00:00.000+01:00",
    "PT-Cross border electricity trading": 2520.9,
    "PT-Biomass": 347.9,
    "PT-Others": 21.3,
    "PT-Solar": 0,
    "PT-Load": 4932.8,
    "PT-Residual load": 2374.7,
    "PT-Renewable share of generation": 94.1,
    "PT-Renewable share of load": 73.2,
    "PT-undefined": 25.61,
    "PT-Hydro Pumped": -1396,
    "PT-Wind": 2558.1,
    "PT-Coal": null,
    "PT-Hydro": -690.2,
    "PT-Import": null,
    "PT-Gas": 180.7
  },
  {
    "x": "2024-01-02T02:00:00.000+01:00",
    "PT-Cross border electricity trading": 2538,
    "PT-Biomass": 353.3,
    "PT-Others": 20.9,
    "PT-Solar": 0,
    "PT-Load": 4561.3,
    "PT-Residual load": 1923.5,
    "PT-Renewable share of generation": 94.7,
    "PT-Renewable share of load": 78.5,
    "PT-undefined": 20.61,
    "PT-Hydro Pumped": -1730.2,
    "PT-Wind": 2637.8,
    "PT-Coal": null,
    "PT-Hydro": -1141.6,
    "PT-Import": null,
    "PT-Gas": 180.6
  },
  {
    "x": "2024-01-02T03:00:00.000+01:00",
    "PT-Cross border electricity trading": 2506.6,
    "PT-Biomass": 351.2,
    "PT-Others": 21.2,
    "PT-Solar": 0,
    "PT-Load": 4325.1,
    "PT-Residual load": 1397.6,
    "PT-Renewable share of generation": 94.9,
    "PT-Renewable share of load": 87.2,
    "PT-undefined": 14.54,
    "PT-Hydro Pumped": -2134.4,
    "PT-Wind": 2927.5,
    "PT-Coal": null,
    "PT-Hydro": -1639.6,
    "PT-Import": null,
    "PT-Gas": 180.3
  },
  {
    "x": "2024-01-02T04:00:00.000+01:00",
    "PT-Cross border electricity trading": 2617.1,
    "PT-Biomass": 353.8,
    "PT-Others": 21.1,
    "PT-Solar": 0,
    "PT-Load": 4194,
    "PT-Residual load": 847.4,
    "PT-Renewable share of generation": 95.3,
    "PT-Renewable share of load": 97.3,
    "PT-undefined": 13.21,
    "PT-Hydro Pumped": -2350.3,
    "PT-Wind": 3346.6,
    "PT-Coal": null,
    "PT-Hydro": -1971.2000000000003,
    "PT-Import": null,
    "PT-Gas": 180.4
  },
  {
    "x": "2024-01-02T05:00:00.000+01:00",
    "PT-Cross border electricity trading": 2416.9,
    "PT-Biomass": 351.2,
    "PT-Others": 20.7,
    "PT-Solar": 0,
    "PT-Load": 4184,
    "PT-Residual load": 712.1,
    "PT-Renewable share of generation": 95.4,
    "PT-Renewable share of load": 99.4,
    "PT-undefined": 14.54,
    "PT-Hydro Pumped": -2265,
    "PT-Wind": 3471.9,
    "PT-Coal": null,
    "PT-Hydro": -1927.5,
    "PT-Import": null,
    "PT-Gas": 180.3
  },
  {
    "x": "2024-01-02T06:00:00.000+01:00",
    "PT-Cross border electricity trading": 1566.7,
    "PT-Biomass": 349.1,
    "PT-Others": 20.2,
    "PT-Solar": 0,
    "PT-Load": 4277.4,
    "PT-Residual load": 897.4,
    "PT-Renewable share of generation": 92,
    "PT-Renewable share of load": 94.5,
    "PT-undefined": 36.29,
    "PT-Hydro Pumped": -1856.5,
    "PT-Wind": 3380,
    "PT-Coal": null,
    "PT-Hydro": -1542.9,
    "PT-Import": null,
    "PT-Gas": 179.8
  },
  {
    "x": "2024-01-02T07:00:00.000+01:00",
    "PT-Cross border electricity trading": 1787.8,
    "PT-Biomass": 355.7,
    "PT-Others": 21.5,
    "PT-Solar": 0,
    "PT-Load": 4668.2,
    "PT-Residual load": 1096.7,
    "PT-Renewable share of generation": 92.5,
    "PT-Renewable share of load": 93.1,
    "PT-undefined": 44.7,
    "PT-Hydro Pumped": -1914.9999999999998,
    "PT-Wind": 3571.5,
    "PT-Coal": null,
    "PT-Hydro": -1496.8999999999999,
    "PT-Import": null,
    "PT-Gas": 186.7
  },
  {
    "x": "2024-01-02T08:00:00.000+01:00",
    "PT-Cross border electricity trading": 9.3,
    "PT-Biomass": 354,
    "PT-Others": 21.2,
    "PT-Solar": 0.7,
    "PT-Load": 5146.7,
    "PT-Residual load": 1402.1,
    "PT-Renewable share of generation": 84,
    "PT-Renewable share of load": 96.2,
    "PT-undefined": 53.78,
    "PT-Hydro Pumped": 88.89999999999998,
    "PT-Wind": 3743.9,
    "PT-Coal": null,
    "PT-Hydro": 940.6,
    "PT-Import": null,
    "PT-Gas": 214
  },
  {
    "x": "2024-01-02T09:00:00.000+01:00",
    "PT-Cross border electricity trading": -397.2,
    "PT-Biomass": 349.8,
    "PT-Others": 20.9,
    "PT-Solar": 99.2,
    "PT-Load": 5866.5,
    "PT-Residual load": 2076.2,
    "PT-Renewable share of generation": 79.9,
    "PT-Renewable share of load": 86.3,
    "PT-undefined": 54.23,
    "PT-Hydro Pumped": 780.2,
    "PT-Wind": 3691.1,
    "PT-Coal": null,
    "PT-Hydro": 1703.6,
    "PT-Import": null,
    "PT-Gas": 219.8
  },
  {
    "x": "2024-01-02T10:00:00.000+01:00",
    "PT-Cross border electricity trading": 738,
    "PT-Biomass": 344.8,
    "PT-Others": 20.9,
    "PT-Solar": 388,
    "PT-Load": 6484.5,
    "PT-Residual load": 2385.2,
    "PT-Renewable share of generation": 82.8,
    "PT-Renewable share of load": 79.2,
    "PT-undefined": 50,
    "PT-Hydro Pumped": 365.9,
    "PT-Wind": 3711.3,
    "PT-Coal": null,
    "PT-Hydro": 1056.2,
    "PT-Import": null,
    "PT-Gas": 222.7
  },
  {
    "x": "2024-01-02T11:00:00.000+01:00",
    "PT-Cross border electricity trading": 1714.2,
    "PT-Biomass": 346,
    "PT-Others": 19.8,
    "PT-Solar": 723.9,
    "PT-Load": 6816.6,
    "PT-Residual load": 2298.9,
    "PT-Renewable share of generation": 88.8,
    "PT-Renewable share of load": 77.6,
    "PT-undefined": 52.2,
    "PT-Hydro Pumped": -398.59999999999997,
    "PT-Wind": 3793.8,
    "PT-Coal": null,
    "PT-Hydro": 28.399999999999977,
    "PT-Import": null,
    "PT-Gas": 219.3
  },
  {
    "x": "2024-01-02T12:00:00.000+01:00",
    "PT-Cross border electricity trading": 3139.5,
    "PT-Biomass": 347.9,
    "PT-Others": 21.6,
    "PT-Solar": 876.8,
    "PT-Load": 7167.6,
    "PT-Residual load": 2241.7,
    "PT-Renewable share of generation": 96,
    "PT-Renewable share of load": 82.2,
    "PT-undefined": 45,
    "PT-Hydro Pumped": -2052.6,
    "PT-Wind": 4049.1,
    "PT-Coal": null,
    "PT-Hydro": -1437.3999999999999,
    "PT-Import": null,
    "PT-Gas": 219.5
  },
  {
    "x": "2024-01-02T13:00:00.000+01:00",
    "PT-Cross border electricity trading": 3150,
    "PT-Biomass": 352.1,
    "PT-Others": 21.4,
    "PT-Solar": 824.4,
    "PT-Load": 7368.2,
    "PT-Residual load": 2386.2,
    "PT-Renewable share of generation": 93.1,
    "PT-Renewable share of load": 81.3,
    "PT-undefined": 43,
    "PT-Hydro Pumped": -1772.1000000000001,
    "PT-Wind": 4157.6,
    "PT-Coal": null,
    "PT-Hydro": -1116.7,
    "PT-Import": null,
    "PT-Gas": 219.4
  },
  {
    "x": "2024-01-02T14:00:00.000+01:00",
    "PT-Cross border electricity trading": 2994.1,
    "PT-Biomass": 354.2,
    "PT-Others": 21.8,
    "PT-Solar": 711.6,
    "PT-Load": 7454.5,
    "PT-Residual load": 2507.5,
    "PT-Renewable share of generation": 94.3,
    "PT-Renewable share of load": 80,
    "PT-undefined": 43,
    "PT-Hydro Pumped": -1804.7,
    "PT-Wind": 4235.4,
    "PT-Coal": null,
    "PT-Hydro": -1145.3,
    "PT-Import": null,
    "PT-Gas": 220.8
  },
  {
    "x": "2024-01-02T15:00:00.000+01:00",
    "PT-Cross border electricity trading": 2685.4,
    "PT-Biomass": 351.9,
    "PT-Others": 21.3,
    "PT-Solar": 521.1,
    "PT-Load": 7513.1,
    "PT-Residual load": 2692.6,
    "PT-Renewable share of generation": 94.1,
    "PT-Renewable share of load": 78.7,
    "PT-undefined": 40.99,
    "PT-Hydro Pumped": -1448.1000000000001,
    "PT-Wind": 4299.4,
    "PT-Coal": null,
    "PT-Hydro": -709.3000000000001,
    "PT-Import": null,
    "PT-Gas": 219.7
  },
  {
    "x": "2024-01-02T16:00:00.000+01:00",
    "PT-Cross border electricity trading": 2768.6,
    "PT-Biomass": 345,
    "PT-Others": 21.7,
    "PT-Solar": 337.6,
    "PT-Load": 7503.9,
    "PT-Residual load": 2907,
    "PT-Renewable share of generation": 94.4,
    "PT-Renewable share of load": 75.6,
    "PT-undefined": 43.66,
    "PT-Hydro Pumped": -1249.7,
    "PT-Wind": 4259.3,
    "PT-Coal": null,
    "PT-Hydro": -519.8000000000001,
    "PT-Import": null,
    "PT-Gas": 219.7
  },
  {
    "x": "2024-01-02T17:00:00.000+01:00",
    "PT-Cross border electricity trading": 2067.6,
    "PT-Biomass": 350.3,
    "PT-Others": 21.8,
    "PT-Solar": 119.6,
    "PT-Load": 7533.4,
    "PT-Residual load": 3247.1,
    "PT-Renewable share of generation": 90.1,
    "PT-Renewable share of load": 76.8,
    "PT-undefined": 52.2,
    "PT-Hydro Pumped": -275.5,
    "PT-Wind": 4166.7,
    "PT-Coal": null,
    "PT-Hydro": 872.6999999999999,
    "PT-Import": null,
    "PT-Gas": 220.5
  },
  {
    "x": "2024-01-02T18:00:00.000+01:00",
    "PT-Cross border electricity trading": 1160.1,
    "PT-Biomass": 348.2,
    "PT-Others": 22,
    "PT-Solar": 3.9,
    "PT-Load": 7850.5,
    "PT-Residual load": 3837.3,
    "PT-Renewable share of generation": 85.1,
    "PT-Renewable share of load": 71.8,
    "PT-undefined": 57.77,
    "PT-Hydro Pumped": 728.3,
    "PT-Wind": 4009.3,
    "PT-Coal": null,
    "PT-Hydro": 2005.6,
    "PT-Import": null,
    "PT-Gas": 222.3
  },
  {
    "x": "2024-01-02T19:00:00.000+01:00",
    "PT-Cross border electricity trading": 306.9,
    "PT-Biomass": 343.7,
    "PT-Others": 21.5,
    "PT-Solar": 0,
    "PT-Load": 8139.4,
    "PT-Residual load": 4348.5,
    "PT-Renewable share of generation": 76.1,
    "PT-Renewable share of load": 71,
    "PT-undefined": 62.45,
    "PT-Hydro Pumped": 1575.6,
    "PT-Wind": 3790.9,
    "PT-Coal": null,
    "PT-Hydro": 3216.1,
    "PT-Import": null,
    "PT-Gas": 219.7
  },
  {
    "x": "2024-01-02T20:00:00.000+01:00",
    "PT-Cross border electricity trading": 1637.2,
    "PT-Biomass": 346.2,
    "PT-Others": 22.2,
    "PT-Solar": 0,
    "PT-Load": 8338.4,
    "PT-Residual load": 4677.7,
    "PT-Renewable share of generation": 83.1,
    "PT-Renewable share of load": 66.3,
    "PT-undefined": 58,
    "PT-Hydro Pumped": 844.7,
    "PT-Wind": 3660.7,
    "PT-Coal": null,
    "PT-Hydro": 2369.9,
    "PT-Import": null,
    "PT-Gas": 217.7
  },
  {
    "x": "2024-01-02T21:00:00.000+01:00",
    "PT-Cross border electricity trading": 2388.8,
    "PT-Biomass": 345.6,
    "PT-Others": 22.1,
    "PT-Solar": 0,
    "PT-Load": 8179.8,
    "PT-Residual load": 4508.5,
    "PT-Renewable share of generation": 85.5,
    "PT-Renewable share of load": 64.5,
    "PT-undefined": 52.83,
    "PT-Hydro Pumped": 71.69999999999993,
    "PT-Wind": 3671.2999999999997,
    "PT-Coal": null,
    "PT-Hydro": 1328.6,
    "PT-Import": null,
    "PT-Gas": 218.7
  },
  {
    "x": "2024-01-02T22:00:00.000+01:00",
    "PT-Cross border electricity trading": 3060,
    "PT-Biomass": 350.2,
    "PT-Others": 24,
    "PT-Solar": 0,
    "PT-Load": 7724.5,
    "PT-Residual load": 4193.3,
    "PT-Renewable share of generation": 84.9,
    "PT-Renewable share of load": 64.3,
    "PT-undefined": 46.26,
    "PT-Hydro Pumped": -270.70000000000005,
    "PT-Wind": 3531.2,
    "PT-Coal": null,
    "PT-Hydro": 813.5,
    "PT-Import": null,
    "PT-Gas": 218.1
  },
  {
    "x": "2024-01-02T23:00:00.000+01:00",
    "PT-Cross border electricity trading": 3060,
    "PT-Biomass": 350.4,
    "PT-Others": 24.4,
    "PT-Solar": 0,
    "PT-Load": 7059.7,
    "PT-Residual load": 3663.8,
    "PT-Renewable share of generation": 81.9,
    "PT-Renewable share of load": 68.9,
    "PT-undefined": 40.1,
    "PT-Hydro Pumped": -523.1,
    "PT-Wind": 3395.8999999999996,
    "PT-Coal": null,
    "PT-Hydro": 593.1,
    "PT-Import": null,
    "PT-Gas": 218.4
  },
  {
    "x": "2024-01-03T00:00:00.000+01:00",
    "PT-Cross border electricity trading": 2502,
    "PT-Biomass": 348,
    "PT-Others": 24,
    "PT-Solar": 0,
    "PT-Load": 6222.5,
    "PT-Residual load": 3109,
    "PT-Renewable share of generation": 87,
    "PT-Renewable share of load": 67,
    "PT-undefined": 6.8,
    "PT-Hydro Pumped": -633.1,
    "PT-Wind": 3113.5,
    "PT-Coal": null,
    "PT-Hydro": 73.5,
    "PT-Import": null,
    "PT-Gas": 212.4
  },
  {
    "x": "2024-01-03T01:00:00.000+01:00",
    "PT-Cross border electricity trading": 2832,
    "PT-Biomass": 351.5,
    "PT-Others": 23.3,
    "PT-Solar": 0,
    "PT-Load": 5330.9,
    "PT-Residual load": 2538.2,
    "PT-Renewable share of generation": 88.4,
    "PT-Renewable share of load": 67.2,
    "PT-undefined": 3.2,
    "PT-Hydro Pumped": -1253.1999999999998,
    "PT-Wind": 2792.7,
    "PT-Coal": null,
    "PT-Hydro": -812.8999999999997,
    "PT-Import": null,
    "PT-Gas": 193
  },
  {
    "x": "2024-01-03T02:00:00.000+01:00",
    "PT-Cross border electricity trading": 2793.5,
    "PT-Biomass": 349.2,
    "PT-Others": 22.9,
    "PT-Solar": 0,
    "PT-Load": 4969.3,
    "PT-Residual load": 2143.1,
    "PT-Renewable share of generation": 91,
    "PT-Renewable share of load": 71.9,
    "PT-undefined": 3.2,
    "PT-Hydro Pumped": -1589.3,
    "PT-Wind": 2826.2000000000003,
    "PT-Coal": null,
    "PT-Hydro": -1193.8000000000002,
    "PT-Import": null,
    "PT-Gas": 186.8
  },
  {
    "x": "2024-01-03T03:00:00.000+01:00",
    "PT-Cross border electricity trading": 2832,
    "PT-Biomass": 345.7,
    "PT-Others": 22.7,
    "PT-Solar": 0,
    "PT-Load": 4726.5,
    "PT-Residual load": 1892.3,
    "PT-Renewable share of generation": 91.3,
    "PT-Renewable share of load": 75.6,
    "PT-undefined": 3.2,
    "PT-Hydro Pumped": -1832.5,
    "PT-Wind": 2834.2,
    "PT-Coal": null,
    "PT-Hydro": -1439.3,
    "PT-Import": null,
    "PT-Gas": 186.9
  },
  {
    "x": "2024-01-03T04:00:00.000+01:00",
    "PT-Cross border electricity trading": 2799.8,
    "PT-Biomass": 347.9,
    "PT-Others": 22.4,
    "PT-Solar": 0,
    "PT-Load": 4527.1,
    "PT-Residual load": 1658.3,
    "PT-Renewable share of generation": 91.3,
    "PT-Renewable share of load": 79.7,
    "PT-undefined": 3.2,
    "PT-Hydro Pumped": -2133.4,
    "PT-Wind": 2868.7999999999997,
    "PT-Coal": null,
    "PT-Hydro": -1739.8000000000002,
    "PT-Import": null,
    "PT-Gas": 188.3
  },
  {
    "x": "2024-01-03T05:00:00.000+01:00",
    "PT-Cross border electricity trading": 2838,
    "PT-Biomass": 346.7,
    "PT-Others": 22.2,
    "PT-Solar": 0,
    "PT-Load": 4382.9,
    "PT-Residual load": 1678.8,
    "PT-Renewable share of generation": 89.1,
    "PT-Renewable share of load": 78.2,
    "PT-undefined": 2.21,
    "PT-Hydro Pumped": -2009.1,
    "PT-Wind": 2704.1000000000004,
    "PT-Coal": null,
    "PT-Hydro": -1630.6,
    "PT-Import": null,
    "PT-Gas": 188.7
  },
  {
    "x": "2024-01-03T06:00:00.000+01:00",
    "PT-Cross border electricity trading": 2116.4,
    "PT-Biomass": 336.5,
    "PT-Others": 20.9,
    "PT-Solar": 0,
    "PT-Load": 2594,
    "PT-Residual load": 2593.7,
    "PT-Renewable share of generation": 61.1,
    "PT-Renewable share of load": 38.3,
    "PT-undefined": 4.78,
    "PT-Hydro Pumped": -567,
    "PT-Wind": 0.3,
    "PT-Coal": null,
    "PT-Hydro": 90.80000000000001,
    "PT-Import": null,
    "PT-Gas": 165.3
  },
  {
    "x": "2024-01-03T07:00:00.000+01:00",
    "PT-Cross border electricity trading": 1435.4,
    "PT-Biomass": 329.3,
    "PT-Others": 20.8,
    "PT-Solar": 0,
    "PT-Load": 3138.4,
    "PT-Residual load": 3138.1,
    "PT-Renewable share of generation": 61.6,
    "PT-Renewable share of load": 32.9,
    "PT-undefined": 45.42,
    "PT-Hydro Pumped": 151.5,
    "PT-Wind": 0.3,
    "PT-Coal": null,
    "PT-Hydro": 855.8,
    "PT-Import": null,
    "PT-Gas": 172.5
  },
  {
    "x": "2024-01-03T08:00:00.000+01:00",
    "PT-Cross border electricity trading": 1183.8,
    "PT-Biomass": 344.8,
    "PT-Others": 22.2,
    "PT-Solar": 0.4,
    "PT-Load": 6066,
    "PT-Residual load": 4130.2,
    "PT-Renewable share of generation": 67,
    "PT-Renewable share of load": 55.1,
    "PT-undefined": 61.92,
    "PT-Hydro Pumped": 1402.8,
    "PT-Wind": 1935.3999999999999,
    "PT-Coal": null,
    "PT-Hydro": 2466.4,
    "PT-Import": null,
    "PT-Gas": 220.3
  },
  {
    "x": "2024-01-03T09:00:00.000+01:00",
    "PT-Cross border electricity trading": 1317.9,
    "PT-Biomass": 355.4,
    "PT-Others": 22.1,
    "PT-Solar": 44.2,
    "PT-Load": 7039.1,
    "PT-Residual load": 5388.3,
    "PT-Renewable share of generation": 63.9,
    "PT-Renewable share of load": 51.5,
    "PT-undefined": 67,
    "PT-Hydro Pumped": 1780.2,
    "PT-Wind": 1606.6,
    "PT-Coal": null,
    "PT-Hydro": 3401.1000000000004,
    "PT-Import": null,
    "PT-Gas": 243.1
  },
  {
    "x": "2024-01-03T10:00:00.000+01:00",
    "PT-Cross border electricity trading": 2533.5,
    "PT-Biomass": 343.2,
    "PT-Others": 22,
    "PT-Solar": 135.7,
    "PT-Load": 7544.4,
    "PT-Residual load": 6281.3,
    "PT-Renewable share of generation": 63.3,
    "PT-Renewable share of load": 42.6,
    "PT-undefined": 63.6,
    "PT-Hydro Pumped": 1598,
    "PT-Wind": 1127.4,
    "PT-Coal": null,
    "PT-Hydro": 3208.1,
    "PT-Import": null,
    "PT-Gas": 246.9
  },
  {
    "x": "2024-01-03T11:00:00.000+01:00",
    "PT-Cross border electricity trading": 3092.3,
    "PT-Biomass": 331.9,
    "PT-Others": 22.1,
    "PT-Solar": 250.3,
    "PT-Load": 7760.2,
    "PT-Residual load": 6621.2,
    "PT-Renewable share of generation": 69.7,
    "PT-Renewable share of load": 41.4,
    "PT-undefined": 58.5,
    "PT-Hydro Pumped": 1122.7,
    "PT-Wind": 888.7,
    "PT-Coal": null,
    "PT-Hydro": 2865.8,
    "PT-Import": null,
    "PT-Gas": 248.2
  },
  {
    "x": "2024-01-03T12:00:00.000+01:00",
    "PT-Cross border electricity trading": 3195,
    "PT-Biomass": 320.2,
    "PT-Others": 22,
    "PT-Solar": 317.3,
    "PT-Load": 7981.3,
    "PT-Residual load": 6687.1,
    "PT-Renewable share of generation": 68.3,
    "PT-Renewable share of load": 41,
    "PT-undefined": 63.6,
    "PT-Hydro Pumped": 1242.5,
    "PT-Wind": 976.9000000000001,
    "PT-Coal": null,
    "PT-Hydro": 2901.8,
    "PT-Import": null,
    "PT-Gas": 253.6
  },
  {
    "x": "2024-01-03T13:00:00.000+01:00",
    "PT-Cross border electricity trading": 3195,
    "PT-Biomass": 327.3,
    "PT-Others": 23.5,
    "PT-Solar": 348,
    "PT-Load": 7900.6,
    "PT-Residual load": 6657.4,
    "PT-Renewable share of generation": 67.3,
    "PT-Renewable share of load": 40.2,
    "PT-undefined": 63.35,
    "PT-Hydro Pumped": 1247.5,
    "PT-Wind": 895.2,
    "PT-Coal": null,
    "PT-Hydro": 2854.4,
    "PT-Import": null,
    "PT-Gas": 272.8
  },
  {
    "x": "2024-01-03T14:00:00.000+01:00",
    "PT-Cross border electricity trading": 3195,
    "PT-Biomass": 328.9,
    "PT-Others": 23.7,
    "PT-Solar": 309.1,
    "PT-Load": 7802.5,
    "PT-Residual load": 6704.5,
    "PT-Renewable share of generation": 66,
    "PT-Renewable share of load": 39.1,
    "PT-undefined": 63.6,
    "PT-Hydro Pumped": 1250.7,
    "PT-Wind": 788.9,
    "PT-Coal": null,
    "PT-Hydro": 2876.8,
    "PT-Import": null,
    "PT-Gas": 296.1
  },
  {
    "x": "2024-01-03T15:00:00.000+01:00",
    "PT-Cross border electricity trading": 3479.8,
    "PT-Biomass": 331,
    "PT-Others": 23.2,
    "PT-Solar": 219.2,
    "PT-Load": 7843.5,
    "PT-Residual load": 6885.4,
    "PT-Renewable share of generation": 61.3,
    "PT-Renewable share of load": 33.8,
    "PT-undefined": 66.03,
    "PT-Hydro Pumped": 1165.5,
    "PT-Wind": 738.9000000000001,
    "PT-Coal": null,
    "PT-Hydro": 2531,
    "PT-Import": null,
    "PT-Gas": 486.3
  },
  {
    "x": "2024-01-03T16:00:00.000+01:00",
    "PT-Cross border electricity trading": 2825.8,
    "PT-Biomass": 345.1,
    "PT-Others": 24.2,
    "PT-Solar": 128.8,
    "PT-Load": 7715,
    "PT-Residual load": 7101.7,
    "PT-Renewable share of generation": 51.2,
    "PT-Renewable share of load": 31.2,
    "PT-undefined": 67.52,
    "PT-Hydro Pumped": 1650.7,
    "PT-Wind": 484.5,
    "PT-Coal": null,
    "PT-Hydro": 3099,
    "PT-Import": null,
    "PT-Gas": 620.6
  },
  {
    "x": "2024-01-03T17:00:00.000+01:00",
    "PT-Cross border electricity trading": 1212.7,
    "PT-Biomass": 349.5,
    "PT-Others": 25.2,
    "PT-Solar": 31,
    "PT-Load": 7780,
    "PT-Residual load": 7382.8,
    "PT-Renewable share of generation": 51.8,
    "PT-Renewable share of load": 34.7,
    "PT-undefined": 89.57,
    "PT-Hydro Pumped": 1682.5,
    "PT-Wind": 366.2,
    "PT-Coal": null,
    "PT-Hydro": 3637.6000000000004,
    "PT-Import": null,
    "PT-Gas": 806
  },
  {
    "x": "2024-01-03T18:00:00.000+01:00",
    "PT-Cross border electricity trading": 318.8,
    "PT-Biomass": 346.2,
    "PT-Others": 25.2,
    "PT-Solar": 0.5,
    "PT-Load": 7991.5,
    "PT-Residual load": 7631.4,
    "PT-Renewable share of generation": 43.4,
    "PT-Renewable share of load": 33.7,
    "PT-undefined": 94.2,
    "PT-Hydro Pumped": 2204.3,
    "PT-Wind": 359.6,
    "PT-Coal": null,
    "PT-Hydro": 4192.9,
    "PT-Import": null,
    "PT-Gas": 1278.1
  },
  {
    "x": "2024-01-03T19:00:00.000+01:00",
    "PT-Cross border electricity trading": 22.6,
    "PT-Biomass": 351.9,
    "PT-Others": 25.2,
    "PT-Solar": 0,
    "PT-Load": 8301.7,
    "PT-Residual load": 7943.4,
    "PT-Renewable share of generation": 44.8,
    "PT-Renewable share of load": 38.2,
    "PT-undefined": 104.35,
    "PT-Hydro Pumped": 2449.6,
    "PT-Wind": 358.3,
    "PT-Coal": null,
    "PT-Hydro": 4909.5,
    "PT-Import": null,
    "PT-Gas": 1425.7
  },
  {
    "x": "2024-01-03T20:00:00.000+01:00",
    "PT-Cross border electricity trading": 575,
    "PT-Biomass": 343.7,
    "PT-Others": 25.1,
    "PT-Solar": 0,
    "PT-Load": 8430.1,
    "PT-Residual load": 8087.1,
    "PT-Renewable share of generation": 49.5,
    "PT-Renewable share of load": 41.2,
    "PT-undefined": 113.26,
    "PT-Hydro Pumped": 2125.4,
    "PT-Wind": 343,
    "PT-Coal": null,
    "PT-Hydro": 4914.6,
    "PT-Import": null,
    "PT-Gas": 1385.8
  },
  {
    "x": "2024-01-03T21:00:00.000+01:00",
    "PT-Cross border electricity trading": 580,
    "PT-Biomass": 347.1,
    "PT-Others": 24.8,
    "PT-Solar": 0,
    "PT-Load": 8333.7,
    "PT-Residual load": 7925.4,
    "PT-Renewable share of generation": 51.5,
    "PT-Renewable share of load": 42,
    "PT-undefined": 113.26,
    "PT-Hydro Pumped": 1879.8,
    "PT-Wind": 408.29999999999995,
    "PT-Coal": null,
    "PT-Hydro": 4621.3,
    "PT-Import": null,
    "PT-Gas": 1388.7
  },
  {
    "x": "2024-01-03T22:00:00.000+01:00",
    "PT-Cross border electricity trading": 1164.7,
    "PT-Biomass": 359.5,
    "PT-Others": 25.2,
    "PT-Solar": 0,
    "PT-Load": 7854.6,
    "PT-Residual load": 7330,
    "PT-Renewable share of generation": 56.7,
    "PT-Renewable share of load": 42.2,
    "PT-undefined": 94.2,
    "PT-Hydro Pumped": 1173,
    "PT-Wind": 524.6,
    "PT-Coal": null,
    "PT-Hydro": 3606.5,
    "PT-Import": null,
    "PT-Gas": 1274.3
  },
  {
    "x": "2024-01-03T23:00:00.000+01:00",
    "PT-Cross border electricity trading": 2774.9,
    "PT-Biomass": 361.2,
    "PT-Others": 23.9,
    "PT-Solar": 0,
    "PT-Load": 7229.2,
    "PT-Residual load": 6426.1,
    "PT-Renewable share of generation": 74.1,
    "PT-Renewable share of load": 43.8,
    "PT-undefined": 86.58,
    "PT-Hydro Pumped": 378.5,
    "PT-Wind": 803.1,
    "PT-Coal": null,
    "PT-Hydro": 2383.3,
    "PT-Import": null,
    "PT-Gas": 700.3
  },
  {
    "x": "2024-01-04T00:00:00.000+01:00",
    "PT-Cross border electricity trading": 2812.9,
    "PT-Biomass": 359.7,
    "PT-Others": 23.9,
    "PT-Solar": 0,
    "PT-Load": 6468.5,
    "PT-Residual load": 5454.4,
    "PT-Renewable share of generation": 76.4,
    "PT-Renewable share of load": 44.2,
    "PT-undefined": 90.39,
    "PT-Hydro Pumped": 248.50000000000003,
    "PT-Wind": 1014.1,
    "PT-Coal": null,
    "PT-Hydro": 1734.2,
    "PT-Import": null,
    "PT-Gas": 534.4
  },
  {
    "x": "2024-01-04T01:00:00.000+01:00",
    "PT-Cross border electricity trading": 2880,
    "PT-Biomass": 323.1,
    "PT-Others": 24.8,
    "PT-Solar": 0,
    "PT-Load": 5684.7,
    "PT-Residual load": 4544.9,
    "PT-Renewable share of generation": 83.5,
    "PT-Renewable share of load": 46.6,
    "PT-undefined": 87,
    "PT-Hydro Pumped": -234.60000000000002,
    "PT-Wind": 1139.8,
    "PT-Coal": null,
    "PT-Hydro": 949.9,
    "PT-Import": null,
    "PT-Gas": 404.1
  },
  {
    "x": "2024-01-04T02:00:00.000+01:00",
    "PT-Cross border electricity trading": 2718.1,
    "PT-Biomass": 318.2,
    "PT-Others": 24.3,
    "PT-Solar": 0,
    "PT-Load": 5186,
    "PT-Residual load": 3975.2,
    "PT-Renewable share of generation": 85.2,
    "PT-Renewable share of load": 49,
    "PT-undefined": 80.21,
    "PT-Hydro Pumped": -459.9,
    "PT-Wind": 1210.8000000000002,
    "PT-Coal": null,
    "PT-Hydro": 552.2,
    "PT-Import": null,
    "PT-Gas": 403.1
  },
  {
    "x": "2024-01-04T03:00:00.000+01:00",
    "PT-Cross border electricity trading": 2705.1,
    "PT-Biomass": 318.3,
    "PT-Others": 24.3,
    "PT-Solar": 0,
    "PT-Load": 5013.7,
    "PT-Residual load": 3687.4,
    "PT-Renewable share of generation": 85,
    "PT-Renewable share of load": 52.5,
    "PT-undefined": 70.1,
    "PT-Hydro Pumped": -721.7,
    "PT-Wind": 1326.3,
    "PT-Coal": null,
    "PT-Hydro": 264.9999999999999,
    "PT-Import": null,
    "PT-Gas": 409.4
  },
  {
    "x": "2024-01-04T04:00:00.000+01:00",
    "PT-Cross border electricity trading": 2143.1,
    "PT-Biomass": 321.1,
    "PT-Others": 22.3,
    "PT-Solar": 0,
    "PT-Load": 4893.3,
    "PT-Residual load": 3513.4,
    "PT-Renewable share of generation": 84.4,
    "PT-Renewable share of load": 59.1,
    "PT-undefined": 66.86,
    "PT-Hydro Pumped": -721.4,
    "PT-Wind": 1379.9,
    "PT-Coal": null,
    "PT-Hydro": 469.6,
    "PT-Import": null,
    "PT-Gas": 417.3
  },
  {
    "x": "2024-01-04T05:00:00.000+01:00",
    "PT-Cross border electricity trading": 1732.4,
    "PT-Biomass": 325.5,
    "PT-Others": 24,
    "PT-Solar": 0,
    "PT-Load": 4843.4,
    "PT-Residual load": 3521.4,
    "PT-Renewable share of generation": 86.4,
    "PT-Renewable share of load": 63.6,
    "PT-undefined": 68.14,
    "PT-Hydro Pumped": -506.00000000000006,
    "PT-Wind": 1322,
    "PT-Coal": null,
    "PT-Hydro": 926,
    "PT-Import": null,
    "PT-Gas": 419.8
  },
  {
    "x": "2024-01-04T06:00:00.000+01:00",
    "PT-Cross border electricity trading": 1037.2,
    "PT-Biomass": 321,
    "PT-Others": 23.1,
    "PT-Solar": 0,
    "PT-Load": 5025.3,
    "PT-Residual load": 3758.1,
    "PT-Renewable share of generation": 80.6,
    "PT-Renewable share of load": 63.7,
    "PT-undefined": 86.74,
    "PT-Hydro Pumped": 238.4,
    "PT-Wind": 1267.2,
    "PT-Coal": null,
    "PT-Hydro": 1850.2,
    "PT-Import": null,
    "PT-Gas": 494.2
  },
  {
    "x": "2024-01-04T07:00:00.000+01:00",
    "PT-Cross border electricity trading": -449.9,
    "PT-Biomass": 324.8,
    "PT-Others": 23,
    "PT-Solar": 0,
    "PT-Load": 5427.1,
    "PT-Residual load": 4224.7,
    "PT-Renewable share of generation": 67.9,
    "PT-Renewable share of load": 68.4,
    "PT-undefined": 94.51,
    "PT-Hydro Pumped": 1192.8,
    "PT-Wind": 1202.4,
    "PT-Coal": null,
    "PT-Hydro": 3378.2,
    "PT-Import": null,
    "PT-Gas": 533.3
  },
  {
    "x": "2024-01-04T08:00:00.000+01:00",
    "PT-Cross border electricity trading": -1027.9,
    "PT-Biomass": 327,
    "PT-Others": 23,
    "PT-Solar": 0,
    "PT-Load": 6332.6,
    "PT-Residual load": 5285.6,
    "PT-Renewable share of generation": 58.4,
    "PT-Renewable share of load": 65,
    "PT-undefined": 96,
    "PT-Hydro Pumped": 2235,
    "PT-Wind": 1047,
    "PT-Coal": null,
    "PT-Hydro": 4980,
    "PT-Import": null,
    "PT-Gas": 673
  },
  {
    "x": "2024-01-04T09:00:00.000+01:00",
    "PT-Cross border electricity trading": -1477.6,
    "PT-Biomass": 334,
    "PT-Others": 23,
    "PT-Solar": 66,
    "PT-Load": 7251.7,
    "PT-Residual load": 6200.7,
    "PT-Renewable share of generation": 55.2,
    "PT-Renewable share of load": 61.3,
    "PT-undefined": 98.13,
    "PT-Hydro Pumped": 2655,
    "PT-Wind": 985,
    "PT-Coal": null,
    "PT-Hydro": 5713,
    "PT-Import": null,
    "PT-Gas": 923
  },
  {
    "x": "2024-01-04T10:00:00.000+01:00",
    "PT-Cross border electricity trading": 393.6,
    "PT-Biomass": 340,
    "PT-Others": 25,
    "PT-Solar": 147,
    "PT-Load": 7558,
    "PT-Residual load": 6354,
    "PT-Renewable share of generation": 62.9,
    "PT-Renewable share of load": 56,
    "PT-undefined": 95,
    "PT-Hydro Pumped": 1520,
    "PT-Wind": 1057,
    "PT-Coal": null,
    "PT-Hydro": 4211,
    "PT-Import": null,
    "PT-Gas": 951
  },
  {
    "x": "2024-01-04T11:00:00.000+01:00",
    "PT-Cross border electricity trading": 1353.1,
    "PT-Biomass": 343,
    "PT-Others": 24,
    "PT-Solar": 294,
    "PT-Load": 7590,
    "PT-Residual load": 6264,
    "PT-Renewable share of generation": 65,
    "PT-Renewable share of load": 53.5,
    "PT-undefined": 90.35,
    "PT-Hydro Pumped": 1218,
    "PT-Wind": 1032,
    "PT-Coal": null,
    "PT-Hydro": 3611,
    "PT-Import": null,
    "PT-Gas": 946
  }
]